{"results":[{"columns":[{"name":"C_PROCESO","type":"NUMBER"},{"name":"C_FILE_UPLOAD","type":"NUMBER"},{"name":"N_PRESTACION","type":"NUMBER"},{"name":"C_VALIDACION","type":"NUMBER"},{"name":"C_GRUPO","type":"CHAR"},{"name":"C_ID_PRACTICA","type":"NUMBER"},{"name":"D_VALIDACION","type":"VARCHAR2"}],"items":
[
{"c_proceso":4821,"c_file_upload":3398291,"n_prestacion":770,"c_validacion":19,"c_grupo":"4 ","c_id_practica":2860668089,"d_validacion":"SOLAPAMIENTO DE INTERNACIONES"}
,{"c_proceso":4821,"c_file_upload":3398291,"n_prestacion":770,"c_validacion":19,"c_grupo":"4 ","c_id_practica":2860683473,"d_validacion":"SOLAPAMIENTO DE INTERNACIONES"}
,{"c_proceso":4821,"c_file_upload":3398291,"n_prestacion":769,"c_validacion":19,"c_grupo":"4 ","c_id_practica":2860670775,"d_validacion":"SOLAPAMIENTO DE INTERNACIONES"}
,{"c_proceso":4821,"c_file_upload":3398291,"n_prestacion":769,"c_validacion":19,"c_grupo":"4 ","c_id_practica":2860670660,"d_validacion":"SOLAPAMIENTO DE INTERNACIONES"}
,{"c_proceso":4821,"c_file_upload":3398291,"n_prestacion":769,"c_validacion":19,"c_grupo":"4 ","c_id_practica":2860668285,"d_validacion":"SOLAPAMIENTO DE INTERNACIONES"}
,{"c_proceso":4821,"c_file_upload":3398291,"n_prestacion":769,"c_validacion":19,"c_grupo":"4 ","c_id_practica":2860686155,"d_validacion":"SOLAPAMIENTO DE INTERNACIONES"}
,{"c_proceso":4821,"c_file_upload":3398291,"n_prestacion":770,"c_validacion":19,"c_grupo":"4 ","c_id_practica":2860686087,"d_validacion":"SOLAPAMIENTO DE INTERNACIONES"}
,{"c_proceso":4821,"c_file_upload":3398291,"n_prestacion":770,"c_validacion":19,"c_grupo":"4 ","c_id_practica":2860680924,"d_validacion":"SOLAPAMIENTO DE INTERNACIONES"}
,{"c_proceso":4821,"c_file_upload":3398291,"n_prestacion":769,"c_validacion":19,"c_grupo":"4 ","c_id_practica":2860670787,"d_validacion":"SOLAPAMIENTO DE INTERNACIONES"}
,{"c_proceso":4821,"c_file_upload":3398291,"n_prestacion":769,"c_validacion":19,"c_grupo":"4 ","c_id_practica":2860678475,"d_validacion":"SOLAPAMIENTO DE INTERNACIONES"}
,{"c_proceso":4821,"c_file_upload":3398291,"n_prestacion":770,"c_validacion":19,"c_grupo":"4 ","c_id_practica":2860673132,"d_validacion":"SOLAPAMIENTO DE INTERNACIONES"}
,{"c_proceso":4821,"c_file_upload":3398291,"n_prestacion":770,"c_validacion":19,"c_grupo":"4 ","c_id_practica":2860673225,"d_validacion":"SOLAPAMIENTO DE INTERNACIONES"}
,{"c_proceso":4821,"c_file_upload":3398291,"n_prestacion":769,"c_validacion":19,"c_grupo":"4 ","c_id_practica":2860673319,"d_validacion":"SOLAPAMIENTO DE INTERNACIONES"}
,{"c_proceso":4821,"c_file_upload":3398291,"n_prestacion":769,"c_validacion":19,"c_grupo":"4 ","c_id_practica":2860673206,"d_validacion":"SOLAPAMIENTO DE INTERNACIONES"}
,{"c_proceso":4821,"c_file_upload":3398291,"n_prestacion":770,"c_validacion":19,"c_grupo":"4 ","c_id_practica":2860673129,"d_validacion":"SOLAPAMIENTO DE INTERNACIONES"}
,{"c_proceso":4821,"c_file_upload":3398291,"n_prestacion":770,"c_validacion":19,"c_grupo":"4 ","c_id_practica":2860670721,"d_validacion":"SOLAPAMIENTO DE INTERNACIONES"}
,{"c_proceso":4821,"c_file_upload":3398291,"n_prestacion":769,"c_validacion":19,"c_grupo":"4 ","c_id_practica":2860686239,"d_validacion":"SOLAPAMIENTO DE INTERNACIONES"}
,{"c_proceso":4821,"c_file_upload":3398291,"n_prestacion":769,"c_validacion":19,"c_grupo":"4 ","c_id_practica":2860675813,"d_validacion":"SOLAPAMIENTO DE INTERNACIONES"}
,{"c_proceso":4821,"c_file_upload":3398291,"n_prestacion":770,"c_validacion":19,"c_grupo":"4 ","c_id_practica":2860678389,"d_validacion":"SOLAPAMIENTO DE INTERNACIONES"}
,{"c_proceso":4821,"c_file_upload":3398291,"n_prestacion":770,"c_validacion":19,"c_grupo":"4 ","c_id_practica":2860675848,"d_validacion":"SOLAPAMIENTO DE INTERNACIONES"}
,{"c_proceso":4821,"c_file_upload":3398291,"n_prestacion":769,"c_validacion":19,"c_grupo":"4 ","c_id_practica":2860678593,"d_validacion":"SOLAPAMIENTO DE INTERNACIONES"}
,{"c_proceso":4821,"c_file_upload":3398291,"n_prestacion":769,"c_validacion":19,"c_grupo":"4 ","c_id_practica":2860683453,"d_validacion":"SOLAPAMIENTO DE INTERNACIONES"}
,{"c_proceso":4821,"c_file_upload":3398291,"n_prestacion":770,"c_validacion":19,"c_grupo":"4 ","c_id_practica":2860678386,"d_validacion":"SOLAPAMIENTO DE INTERNACIONES"}
,{"c_proceso":4821,"c_file_upload":3398291,"n_prestacion":770,"c_validacion":19,"c_grupo":"4 ","c_id_practica":2860678502,"d_validacion":"SOLAPAMIENTO DE INTERNACIONES"}
,{"c_proceso":4821,"c_file_upload":3398291,"n_prestacion":769,"c_validacion":19,"c_grupo":"4 ","c_id_practica":2860686236,"d_validacion":"SOLAPAMIENTO DE INTERNACIONES"}
,{"c_proceso":4821,"c_file_upload":3398291,"n_prestacion":769,"c_validacion":19,"c_grupo":"4 ","c_id_practica":2860668168,"d_validacion":"SOLAPAMIENTO DE INTERNACIONES"}
,{"c_proceso":4821,"c_file_upload":3398291,"n_prestacion":770,"c_validacion":19,"c_grupo":"4 ","c_id_practica":2860678384,"d_validacion":"SOLAPAMIENTO DE INTERNACIONES"}
,{"c_proceso":4821,"c_file_upload":3398291,"n_prestacion":770,"c_validacion":19,"c_grupo":"4 ","c_id_practica":2860670719,"d_validacion":"SOLAPAMIENTO DE INTERNACIONES"}
,{"c_proceso":4821,"c_file_upload":3398291,"n_prestacion":769,"c_validacion":19,"c_grupo":"4 ","c_id_practica":2860668282,"d_validacion":"SOLAPAMIENTO DE INTERNACIONES"}
,{"c_proceso":4821,"c_file_upload":3398291,"n_prestacion":769,"c_validacion":19,"c_grupo":"4 ","c_id_practica":2860683449,"d_validacion":"SOLAPAMIENTO DE INTERNACIONES"}
,{"c_proceso":4821,"c_file_upload":3398291,"n_prestacion":770,"c_validacion":19,"c_grupo":"4 ","c_id_practica":2860673126,"d_validacion":"SOLAPAMIENTO DE INTERNACIONES"}
,{"c_proceso":4821,"c_file_upload":3398291,"n_prestacion":770,"c_validacion":19,"c_grupo":"4 ","c_id_practica":2860683469,"d_validacion":"SOLAPAMIENTO DE INTERNACIONES"}
,{"c_proceso":4821,"c_file_upload":3398291,"n_prestacion":769,"c_validacion":19,"c_grupo":"4 ","c_id_practica":2860670784,"d_validacion":"SOLAPAMIENTO DE INTERNACIONES"}
,{"c_proceso":4821,"c_file_upload":3398291,"n_prestacion":769,"c_validacion":19,"c_grupo":"4 ","c_id_practica":2860678472,"d_validacion":"SOLAPAMIENTO DE INTERNACIONES"}
,{"c_proceso":4821,"c_file_upload":3398291,"n_prestacion":770,"c_validacion":19,"c_grupo":"4 ","c_id_practica":2860675742,"d_validacion":"SOLAPAMIENTO DE INTERNACIONES"}
,{"c_proceso":4821,"c_file_upload":3398291,"n_prestacion":770,"c_validacion":19,"c_grupo":"4 ","c_id_practica":2860673223,"d_validacion":"SOLAPAMIENTO DE INTERNACIONES"}
,{"c_proceso":4821,"c_file_upload":3398291,"n_prestacion":769,"c_validacion":19,"c_grupo":"4 ","c_id_practica":2860683614,"d_validacion":"SOLAPAMIENTO DE INTERNACIONES"}
,{"c_proceso":4821,"c_file_upload":3398291,"n_prestacion":769,"c_validacion":19,"c_grupo":"4 ","c_id_practica":2860678469,"d_validacion":"SOLAPAMIENTO DE INTERNACIONES"}
,{"c_proceso":4821,"c_file_upload":3398291,"n_prestacion":770,"c_validacion":19,"c_grupo":"4 ","c_id_practica":2860668086,"d_validacion":"SOLAPAMIENTO DE INTERNACIONES"}
,{"c_proceso":4821,"c_file_upload":3398291,"n_prestacion":770,"c_validacion":19,"c_grupo":"4 ","c_id_practica":2860668186,"d_validacion":"SOLAPAMIENTO DE INTERNACIONES"}
,{"c_proceso":4821,"c_file_upload":3398291,"n_prestacion":769,"c_validacion":19,"c_grupo":"4 ","c_id_practica":2860673316,"d_validacion":"SOLAPAMIENTO DE INTERNACIONES"}
,{"c_proceso":4821,"c_file_upload":3398291,"n_prestacion":769,"c_validacion":19,"c_grupo":"4 ","c_id_practica":2860678466,"d_validacion":"SOLAPAMIENTO DE INTERNACIONES"}
,{"c_proceso":4821,"c_file_upload":3398291,"n_prestacion":770,"c_validacion":19,"c_grupo":"4 ","c_id_practica":2860683358,"d_validacion":"SOLAPAMIENTO DE INTERNACIONES"}
,{"c_proceso":4821,"c_file_upload":3398291,"n_prestacion":770,"c_validacion":19,"c_grupo":"4 ","c_id_practica":2860670716,"d_validacion":"SOLAPAMIENTO DE INTERNACIONES"}
,{"c_proceso":4821,"c_file_upload":3398291,"n_prestacion":769,"c_validacion":19,"c_grupo":"4 ","c_id_practica":2860670781,"d_validacion":"SOLAPAMIENTO DE INTERNACIONES"}
,{"c_proceso":4821,"c_file_upload":3398291,"n_prestacion":769,"c_validacion":19,"c_grupo":"4 ","c_id_practica":2860675810,"d_validacion":"SOLAPAMIENTO DE INTERNACIONES"}
,{"c_proceso":4821,"c_file_upload":3398291,"n_prestacion":770,"c_validacion":19,"c_grupo":"4 ","c_id_practica":2860673124,"d_validacion":"SOLAPAMIENTO DE INTERNACIONES"}
,{"c_proceso":4821,"c_file_upload":3398291,"n_prestacion":770,"c_validacion":19,"c_grupo":"4 ","c_id_practica":2860670713,"d_validacion":"SOLAPAMIENTO DE INTERNACIONES"}
,{"c_proceso":4821,"c_file_upload":3398291,"n_prestacion":769,"c_validacion":19,"c_grupo":"4 ","c_id_practica":2860673313,"d_validacion":"SOLAPAMIENTO DE INTERNACIONES"}
,{"c_proceso":4821,"c_file_upload":3398291,"n_prestacion":769,"c_validacion":19,"c_grupo":"4 ","c_id_practica":2860678462,"d_validacion":"SOLAPAMIENTO DE INTERNACIONES"}
,{"c_proceso":4821,"c_file_upload":3398291,"n_prestacion":769,"c_validacion":19,"c_grupo":"4 ","c_id_practica":2860683610,"d_validacion":"SOLAPAMIENTO DE INTERNACIONES"}
,{"c_proceso":4821,"c_file_upload":3398291,"n_prestacion":769,"c_validacion":19,"c_grupo":"4 ","c_id_practica":2860686153,"d_validacion":"SOLAPAMIENTO DE INTERNACIONES"}
,{"c_proceso":4821,"c_file_upload":3398291,"n_prestacion":769,"c_validacion":19,"c_grupo":"4 ","c_id_practica":2860673310,"d_validacion":"SOLAPAMIENTO DE INTERNACIONES"}
,{"c_proceso":4821,"c_file_upload":3398291,"n_prestacion":769,"c_validacion":19,"c_grupo":"4 ","c_id_practica":2860668165,"d_validacion":"SOLAPAMIENTO DE INTERNACIONES"}
,{"c_proceso":4821,"c_file_upload":3398291,"n_prestacion":769,"c_validacion":19,"c_grupo":"4 ","c_id_practica":2860673307,"d_validacion":"SOLAPAMIENTO DE INTERNACIONES"}
,{"c_proceso":4821,"c_file_upload":3398291,"n_prestacion":769,"c_validacion":19,"c_grupo":"4 ","c_id_practica":2860678460,"d_validacion":"SOLAPAMIENTO DE INTERNACIONES"}
,{"c_proceso":4821,"c_file_upload":3398291,"n_prestacion":769,"c_validacion":19,"c_grupo":"4 ","c_id_practica":2860678590,"d_validacion":"SOLAPAMIENTO DE INTERNACIONES"}
,{"c_proceso":4821,"c_file_upload":3398291,"n_prestacion":769,"c_validacion":19,"c_grupo":"4 ","c_id_practica":2860680916,"d_validacion":"SOLAPAMIENTO DE INTERNACIONES"}
,{"c_proceso":4821,"c_file_upload":3398291,"n_prestacion":769,"c_validacion":19,"c_grupo":"4 ","c_id_practica":2860681005,"d_validacion":"SOLAPAMIENTO DE INTERNACIONES"}
,{"c_proceso":4821,"c_file_upload":3398291,"n_prestacion":769,"c_validacion":19,"c_grupo":"4 ","c_id_practica":2860670657,"d_validacion":"SOLAPAMIENTO DE INTERNACIONES"}
,{"c_proceso":4821,"c_file_upload":3398291,"n_prestacion":769,"c_validacion":19,"c_grupo":"4 ","c_id_practica":2860670778,"d_validacion":"SOLAPAMIENTO DE INTERNACIONES"}
,{"c_proceso":4821,"c_file_upload":3398291,"n_prestacion":769,"c_validacion":19,"c_grupo":"4 ","c_id_practica":2860680913,"d_validacion":"SOLAPAMIENTO DE INTERNACIONES"}
,{"c_proceso":4821,"c_file_upload":3398291,"n_prestacion":769,"c_validacion":19,"c_grupo":"4 ","c_id_practica":2860681002,"d_validacion":"SOLAPAMIENTO DE INTERNACIONES"}
,{"c_proceso":4821,"c_file_upload":3398291,"n_prestacion":769,"c_validacion":19,"c_grupo":"4 ","c_id_practica":2860670653,"d_validacion":"SOLAPAMIENTO DE INTERNACIONES"}
,{"c_proceso":4821,"c_file_upload":3398291,"n_prestacion":769,"c_validacion":19,"c_grupo":"4 ","c_id_practica":2860686233,"d_validacion":"SOLAPAMIENTO DE INTERNACIONES"}
,{"c_proceso":4821,"c_file_upload":3398291,"n_prestacion":769,"c_validacion":19,"c_grupo":"4 ","c_id_practica":2860675807,"d_validacion":"SOLAPAMIENTO DE INTERNACIONES"}
,{"c_proceso":4821,"c_file_upload":3398291,"n_prestacion":769,"c_validacion":19,"c_grupo":"4 ","c_id_practica":2860673304,"d_validacion":"SOLAPAMIENTO DE INTERNACIONES"}
,{"c_proceso":4821,"c_file_upload":3398291,"n_prestacion":769,"c_validacion":19,"c_grupo":"4 ","c_id_practica":2860668162,"d_validacion":"SOLAPAMIENTO DE INTERNACIONES"}
,{"c_proceso":4821,"c_file_upload":3398291,"n_prestacion":769,"c_validacion":19,"c_grupo":"4 ","c_id_practica":2860678587,"d_validacion":"SOLAPAMIENTO DE INTERNACIONES"}
,{"c_proceso":4821,"c_file_upload":3398291,"n_prestacion":769,"c_validacion":19,"c_grupo":"4 ","c_id_practica":2860686150,"d_validacion":"SOLAPAMIENTO DE INTERNACIONES"}
,{"c_proceso":4821,"c_file_upload":3398291,"n_prestacion":769,"c_validacion":19,"c_grupo":"4 ","c_id_practica":2860683608,"d_validacion":"SOLAPAMIENTO DE INTERNACIONES"}
,{"c_proceso":4821,"c_file_upload":3398291,"n_prestacion":769,"c_validacion":19,"c_grupo":"4 ","c_id_practica":2860673203,"d_validacion":"SOLAPAMIENTO DE INTERNACIONES"}
,{"c_proceso":4821,"c_file_upload":3398291,"n_prestacion":769,"c_validacion":19,"c_grupo":"4 ","c_id_practica":2860673301,"d_validacion":"SOLAPAMIENTO DE INTERNACIONES"}
,{"c_proceso":4821,"c_file_upload":3398291,"n_prestacion":769,"c_validacion":19,"c_grupo":"4 ","c_id_practica":2860683446,"d_validacion":"SOLAPAMIENTO DE INTERNACIONES"}
,{"c_proceso":4821,"c_file_upload":3398291,"n_prestacion":769,"c_validacion":19,"c_grupo":"4 ","c_id_practica":2860683605,"d_validacion":"SOLAPAMIENTO DE INTERNACIONES"}
,{"c_proceso":4821,"c_file_upload":3398291,"n_prestacion":769,"c_validacion":19,"c_grupo":"4 ","c_id_practica":2860686147,"d_validacion":"SOLAPAMIENTO DE INTERNACIONES"}
,{"c_proceso":4821,"c_file_upload":3398291,"n_prestacion":769,"c_validacion":19,"c_grupo":"4 ","c_id_practica":2860675930,"d_validacion":"SOLAPAMIENTO DE INTERNACIONES"}
,{"c_proceso":4821,"c_file_upload":3398291,"n_prestacion":769,"c_validacion":19,"c_grupo":"4 ","c_id_practica":2860686143,"d_validacion":"SOLAPAMIENTO DE INTERNACIONES"}
,{"c_proceso":4821,"c_file_upload":3398291,"n_prestacion":769,"c_validacion":19,"c_grupo":"4 ","c_id_practica":2860686230,"d_validacion":"SOLAPAMIENTO DE INTERNACIONES"}
,{"c_proceso":4821,"c_file_upload":3398291,"n_prestacion":769,"c_validacion":19,"c_grupo":"4 ","c_id_practica":2860675803,"d_validacion":"SOLAPAMIENTO DE INTERNACIONES"}
,{"c_proceso":4821,"c_file_upload":3398291,"n_prestacion":680,"c_validacion":19,"c_grupo":"4 ","c_id_practica":2860668253,"d_validacion":"SOLAPAMIENTO DE INTERNACIONES"}
,{"c_proceso":4821,"c_file_upload":3398291,"n_prestacion":680,"c_validacion":19,"c_grupo":"4 ","c_id_practica":2860675547,"d_validacion":"SOLAPAMIENTO DE INTERNACIONES"}
,{"c_proceso":4821,"c_file_upload":3398291,"n_prestacion":769,"c_validacion":19,"c_grupo":"4 ","c_id_practica":2860675927,"d_validacion":"SOLAPAMIENTO DE INTERNACIONES"}
,{"c_proceso":4821,"c_file_upload":3398291,"n_prestacion":769,"c_validacion":19,"c_grupo":"4 ","c_id_practica":2860673200,"d_validacion":"SOLAPAMIENTO DE INTERNACIONES"}
,{"c_proceso":4821,"c_file_upload":3398291,"n_prestacion":769,"c_validacion":19,"c_grupo":"4 ","c_id_practica":2860673298,"d_validacion":"SOLAPAMIENTO DE INTERNACIONES"}
,{"c_proceso":4821,"c_file_upload":3398291,"n_prestacion":769,"c_validacion":19,"c_grupo":"4 ","c_id_practica":2860673197,"d_validacion":"SOLAPAMIENTO DE INTERNACIONES"}
,{"c_proceso":4821,"c_file_upload":3398291,"n_prestacion":769,"c_validacion":23,"c_grupo":"5 ","c_id_practica":2860676113,"d_validacion":"PRACTICAS EXCLUYENTES"}
,{"c_proceso":4821,"c_file_upload":3398291,"n_prestacion":770,"c_validacion":19,"c_grupo":"4 ","c_id_practica":2860678910,"d_validacion":"SOLAPAMIENTO DE INTERNACIONES"}
,{"c_proceso":4821,"c_file_upload":3398291,"n_prestacion":770,"c_validacion":19,"c_grupo":"4 ","c_id_practica":2860676383,"d_validacion":"SOLAPAMIENTO DE INTERNACIONES"}
,{"c_proceso":4821,"c_file_upload":3398291,"n_prestacion":770,"c_validacion":19,"c_grupo":"4 ","c_id_practica":2860666275,"d_validacion":"SOLAPAMIENTO DE INTERNACIONES"}
,{"c_proceso":4821,"c_file_upload":3398291,"n_prestacion":770,"c_validacion":19,"c_grupo":"4 ","c_id_practica":2860673852,"d_validacion":"SOLAPAMIENTO DE INTERNACIONES"}
,{"c_proceso":4821,"c_file_upload":3398291,"n_prestacion":770,"c_validacion":19,"c_grupo":"4 ","c_id_practica":2860679306,"d_validacion":"SOLAPAMIENTO DE INTERNACIONES"}
,{"c_proceso":4821,"c_file_upload":3398291,"n_prestacion":770,"c_validacion":19,"c_grupo":"4 ","c_id_practica":2860676702,"d_validacion":"SOLAPAMIENTO DE INTERNACIONES"}
,{"c_proceso":4821,"c_file_upload":3398291,"n_prestacion":770,"c_validacion":19,"c_grupo":"4 ","c_id_practica":2860674402,"d_validacion":"SOLAPAMIENTO DE INTERNACIONES"}
,{"c_proceso":4821,"c_file_upload":3398291,"n_prestacion":770,"c_validacion":19,"c_grupo":"4 ","c_id_practica":2860681519,"d_validacion":"SOLAPAMIENTO DE INTERNACIONES"}
,{"c_proceso":4821,"c_file_upload":3398291,"n_prestacion":770,"c_validacion":19,"c_grupo":"4 ","c_id_practica":2860683982,"d_validacion":"SOLAPAMIENTO DE INTERNACIONES"}
,{"c_proceso":4821,"c_file_upload":3398291,"n_prestacion":769,"c_validacion":19,"c_grupo":"4 ","c_id_practica":2860679039,"d_validacion":"SOLAPAMIENTO DE INTERNACIONES"}
,{"c_proceso":4821,"c_file_upload":3398291,"n_prestacion":769,"c_validacion":19,"c_grupo":"4 ","c_id_practica":2860681770,"d_validacion":"SOLAPAMIENTO DE INTERNACIONES"}
,{"c_proceso":4821,"c_file_upload":3398291,"n_prestacion":769,"c_validacion":19,"c_grupo":"4 ","c_id_practica":2860676299,"d_validacion":"SOLAPAMIENTO DE INTERNACIONES"}
,{"c_proceso":4821,"c_file_upload":3398291,"n_prestacion":769,"c_validacion":19,"c_grupo":"4 ","c_id_practica":2860674377,"d_validacion":"SOLAPAMIENTO DE INTERNACIONES"}
,{"c_proceso":4821,"c_file_upload":3398291,"n_prestacion":769,"c_validacion":19,"c_grupo":"4 ","c_id_practica":2860668408,"d_validacion":"SOLAPAMIENTO DE INTERNACIONES"}
,{"c_proceso":4821,"c_file_upload":3398291,"n_prestacion":769,"c_validacion":19,"c_grupo":"4 ","c_id_practica":2860668747,"d_validacion":"SOLAPAMIENTO DE INTERNACIONES"}
,{"c_proceso":4821,"c_file_upload":3398291,"n_prestacion":769,"c_validacion":19,"c_grupo":"4 ","c_id_practica":2860671143,"d_validacion":"SOLAPAMIENTO DE INTERNACIONES"}
,{"c_proceso":4821,"c_file_upload":3398291,"n_prestacion":769,"c_validacion":19,"c_grupo":"4 ","c_id_practica":2860671918,"d_validacion":"SOLAPAMIENTO DE INTERNACIONES"}
,{"c_proceso":4821,"c_file_upload":3398291,"n_prestacion":769,"c_validacion":19,"c_grupo":"4 ","c_id_practica":2860679210,"d_validacion":"SOLAPAMIENTO DE INTERNACIONES"}
,{"c_proceso":4821,"c_file_upload":3398291,"n_prestacion":769,"c_validacion":19,"c_grupo":"4 ","c_id_practica":2860668405,"d_validacion":"SOLAPAMIENTO DE INTERNACIONES"}
,{"c_proceso":4821,"c_file_upload":3398291,"n_prestacion":769,"c_validacion":19,"c_grupo":"4 ","c_id_practica":2860676717,"d_validacion":"SOLAPAMIENTO DE INTERNACIONES"}
,{"c_proceso":4821,"c_file_upload":3398291,"n_prestacion":769,"c_validacion":19,"c_grupo":"4 ","c_id_practica":2860679037,"d_validacion":"SOLAPAMIENTO DE INTERNACIONES"}
,{"c_proceso":4821,"c_file_upload":3398291,"n_prestacion":770,"c_validacion":19,"c_grupo":"4 ","c_id_practica":2860671032,"d_validacion":"SOLAPAMIENTO DE INTERNACIONES"}
,{"c_proceso":4821,"c_file_upload":3398291,"n_prestacion":770,"c_validacion":19,"c_grupo":"4 ","c_id_practica":2860665814,"d_validacion":"SOLAPAMIENTO DE INTERNACIONES"}
,{"c_proceso":4821,"c_file_upload":3398291,"n_prestacion":770,"c_validacion":19,"c_grupo":"4 ","c_id_practica":2860679244,"d_validacion":"SOLAPAMIENTO DE INTERNACIONES"}
,{"c_proceso":4821,"c_file_upload":3398291,"n_prestacion":770,"c_validacion":19,"c_grupo":"4 ","c_id_practica":2860671240,"d_validacion":"SOLAPAMIENTO DE INTERNACIONES"}
,{"c_proceso":4821,"c_file_upload":3398291,"n_prestacion":770,"c_validacion":19,"c_grupo":"4 ","c_id_practica":2860669287,"d_validacion":"SOLAPAMIENTO DE INTERNACIONES"}
,{"c_proceso":4821,"c_file_upload":3398291,"n_prestacion":770,"c_validacion":19,"c_grupo":"4 ","c_id_practica":2860684457,"d_validacion":"SOLAPAMIENTO DE INTERNACIONES"}
,{"c_proceso":4821,"c_file_upload":3398291,"n_prestacion":770,"c_validacion":19,"c_grupo":"4 ","c_id_practica":2860668976,"d_validacion":"SOLAPAMIENTO DE INTERNACIONES"}
,{"c_proceso":4821,"c_file_upload":3398291,"n_prestacion":769,"c_validacion":19,"c_grupo":"4 ","c_id_practica":2860671914,"d_validacion":"SOLAPAMIENTO DE INTERNACIONES"}
,{"c_proceso":4821,"c_file_upload":3398291,"n_prestacion":769,"c_validacion":19,"c_grupo":"4 ","c_id_practica":2860676296,"d_validacion":"SOLAPAMIENTO DE INTERNACIONES"}
,{"c_proceso":4821,"c_file_upload":3398291,"n_prestacion":769,"c_validacion":19,"c_grupo":"4 ","c_id_practica":2860676493,"d_validacion":"SOLAPAMIENTO DE INTERNACIONES"}
,{"c_proceso":4821,"c_file_upload":3398291,"n_prestacion":769,"c_validacion":19,"c_grupo":"4 ","c_id_practica":2860676036,"d_validacion":"SOLAPAMIENTO DE INTERNACIONES"}
,{"c_proceso":4821,"c_file_upload":3398291,"n_prestacion":769,"c_validacion":19,"c_grupo":"4 ","c_id_practica":2860668999,"d_validacion":"SOLAPAMIENTO DE INTERNACIONES"}
,{"c_proceso":4821,"c_file_upload":3398291,"n_prestacion":769,"c_validacion":19,"c_grupo":"4 ","c_id_practica":2860665851,"d_validacion":"SOLAPAMIENTO DE INTERNACIONES"}
,{"c_proceso":4821,"c_file_upload":3398291,"n_prestacion":770,"c_validacion":19,"c_grupo":"4 ","c_id_practica":2860676203,"d_validacion":"SOLAPAMIENTO DE INTERNACIONES"}
,{"c_proceso":4821,"c_file_upload":3398291,"n_prestacion":770,"c_validacion":19,"c_grupo":"4 ","c_id_practica":2860683980,"d_validacion":"SOLAPAMIENTO DE INTERNACIONES"}
,{"c_proceso":4821,"c_file_upload":3398291,"n_prestacion":770,"c_validacion":19,"c_grupo":"4 ","c_id_practica":2860681559,"d_validacion":"SOLAPAMIENTO DE INTERNACIONES"}
,{"c_proceso":4821,"c_file_upload":3398291,"n_prestacion":770,"c_validacion":19,"c_grupo":"4 ","c_id_practica":2860679056,"d_validacion":"SOLAPAMIENTO DE INTERNACIONES"}
,{"c_proceso":4821,"c_file_upload":3398291,"n_prestacion":770,"c_validacion":19,"c_grupo":"4 ","c_id_practica":2860684706,"d_validacion":"SOLAPAMIENTO DE INTERNACIONES"}
,{"c_proceso":4821,"c_file_upload":3398291,"n_prestacion":770,"c_validacion":19,"c_grupo":"4 ","c_id_practica":2860676733,"d_validacion":"SOLAPAMIENTO DE INTERNACIONES"}
,{"c_proceso":4821,"c_file_upload":3398291,"n_prestacion":769,"c_validacion":19,"c_grupo":"4 ","c_id_practica":2860668583,"d_validacion":"SOLAPAMIENTO DE INTERNACIONES"}
,{"c_proceso":4821,"c_file_upload":3398291,"n_prestacion":769,"c_validacion":19,"c_grupo":"4 ","c_id_practica":2860679365,"d_validacion":"SOLAPAMIENTO DE INTERNACIONES"}
,{"c_proceso":4821,"c_file_upload":3398291,"n_prestacion":769,"c_validacion":19,"c_grupo":"4 ","c_id_practica":2860669257,"d_validacion":"SOLAPAMIENTO DE INTERNACIONES"}
,{"c_proceso":4821,"c_file_upload":3398291,"n_prestacion":769,"c_validacion":19,"c_grupo":"4 ","c_id_practica":2860670887,"d_validacion":"SOLAPAMIENTO DE INTERNACIONES"}
,{"c_proceso":4821,"c_file_upload":3398291,"n_prestacion":769,"c_validacion":19,"c_grupo":"4 ","c_id_practica":2860668643,"d_validacion":"SOLAPAMIENTO DE INTERNACIONES"}
,{"c_proceso":4821,"c_file_upload":3398291,"n_prestacion":769,"c_validacion":19,"c_grupo":"4 ","c_id_practica":2860676490,"d_validacion":"SOLAPAMIENTO DE INTERNACIONES"}
,{"c_proceso":4821,"c_file_upload":3398291,"n_prestacion":770,"c_validacion":19,"c_grupo":"4 ","c_id_practica":2860681276,"d_validacion":"SOLAPAMIENTO DE INTERNACIONES"}
,{"c_proceso":4821,"c_file_upload":3398291,"n_prestacion":770,"c_validacion":19,"c_grupo":"4 ","c_id_practica":2860671177,"d_validacion":"SOLAPAMIENTO DE INTERNACIONES"}
,{"c_proceso":4821,"c_file_upload":3398291,"n_prestacion":770,"c_validacion":19,"c_grupo":"4 ","c_id_practica":2860679242,"d_validacion":"SOLAPAMIENTO DE INTERNACIONES"}
,{"c_proceso":4821,"c_file_upload":3398291,"n_prestacion":770,"c_validacion":19,"c_grupo":"4 ","c_id_practica":2860681455,"d_validacion":"SOLAPAMIENTO DE INTERNACIONES"}
,{"c_proceso":4821,"c_file_upload":3398291,"n_prestacion":770,"c_validacion":19,"c_grupo":"4 ","c_id_practica":2860677054,"d_validacion":"SOLAPAMIENTO DE INTERNACIONES"}
,{"c_proceso":4821,"c_file_upload":3398291,"n_prestacion":770,"c_validacion":19,"c_grupo":"4 ","c_id_practica":2860681778,"d_validacion":"SOLAPAMIENTO DE INTERNACIONES"}
,{"c_proceso":4821,"c_file_upload":3398291,"n_prestacion":769,"c_validacion":19,"c_grupo":"4 ","c_id_practica":2860684454,"d_validacion":"SOLAPAMIENTO DE INTERNACIONES"}
,{"c_proceso":4821,"c_file_upload":3398291,"n_prestacion":769,"c_validacion":19,"c_grupo":"4 ","c_id_practica":2860668404,"d_validacion":"SOLAPAMIENTO DE INTERNACIONES"}
,{"c_proceso":4821,"c_file_upload":3398291,"n_prestacion":769,"c_validacion":19,"c_grupo":"4 ","c_id_practica":2860665796,"d_validacion":"SOLAPAMIENTO DE INTERNACIONES"}
,{"c_proceso":4821,"c_file_upload":3398291,"n_prestacion":769,"c_validacion":19,"c_grupo":"4 ","c_id_practica":2860668641,"d_validacion":"SOLAPAMIENTO DE INTERNACIONES"}
,{"c_proceso":4821,"c_file_upload":3398291,"n_prestacion":769,"c_validacion":19,"c_grupo":"4 ","c_id_practica":2860679207,"d_validacion":"SOLAPAMIENTO DE INTERNACIONES"}
,{"c_proceso":4821,"c_file_upload":3398291,"n_prestacion":769,"c_validacion":19,"c_grupo":"4 ","c_id_practica":2860677039,"d_validacion":"SOLAPAMIENTO DE INTERNACIONES"}
,{"c_proceso":4821,"c_file_upload":3398291,"n_prestacion":770,"c_validacion":19,"c_grupo":"4 ","c_id_practica":2860671030,"d_validacion":"SOLAPAMIENTO DE INTERNACIONES"}
,{"c_proceso":4821,"c_file_upload":3398291,"n_prestacion":770,"c_validacion":19,"c_grupo":"4 ","c_id_practica":2860681397,"d_validacion":"SOLAPAMIENTO DE INTERNACIONES"}
,{"c_proceso":4821,"c_file_upload":3398291,"n_prestacion":770,"c_validacion":19,"c_grupo":"4 ","c_id_practica":2860679240,"d_validacion":"SOLAPAMIENTO DE INTERNACIONES"}
,{"c_proceso":4821,"c_file_upload":3398291,"n_prestacion":770,"c_validacion":19,"c_grupo":"4 ","c_id_practica":2860673733,"d_validacion":"SOLAPAMIENTO DE INTERNACIONES"}
,{"c_proceso":4821,"c_file_upload":3398291,"n_prestacion":770,"c_validacion":19,"c_grupo":"4 ","c_id_practica":2860684704,"d_validacion":"SOLAPAMIENTO DE INTERNACIONES"}
,{"c_proceso":4821,"c_file_upload":3398291,"n_prestacion":770,"c_validacion":19,"c_grupo":"4 ","c_id_practica":2860679370,"d_validacion":"SOLAPAMIENTO DE INTERNACIONES"}
,{"c_proceso":4821,"c_file_upload":3398291,"n_prestacion":769,"c_validacion":19,"c_grupo":"4 ","c_id_practica":2860678756,"d_validacion":"SOLAPAMIENTO DE INTERNACIONES"}
,{"c_proceso":4821,"c_file_upload":3398291,"n_prestacion":769,"c_validacion":19,"c_grupo":"4 ","c_id_practica":2860666052,"d_validacion":"SOLAPAMIENTO DE INTERNACIONES"}
,{"c_proceso":4821,"c_file_upload":3398291,"n_prestacion":769,"c_validacion":19,"c_grupo":"4 ","c_id_practica":2860681373,"d_validacion":"SOLAPAMIENTO DE INTERNACIONES"}
,{"c_proceso":4821,"c_file_upload":3398291,"n_prestacion":769,"c_validacion":19,"c_grupo":"4 ","c_id_practica":2860673720,"d_validacion":"SOLAPAMIENTO DE INTERNACIONES"}
,{"c_proceso":4821,"c_file_upload":3398291,"n_prestacion":769,"c_validacion":19,"c_grupo":"4 ","c_id_practica":2860666643,"d_validacion":"SOLAPAMIENTO DE INTERNACIONES"}
,{"c_proceso":4821,"c_file_upload":3398291,"n_prestacion":770,"c_validacion":19,"c_grupo":"4 ","c_id_practica":2860678908,"d_validacion":"SOLAPAMIENTO DE INTERNACIONES"}
,{"c_proceso":4821,"c_file_upload":3398291,"n_prestacion":770,"c_validacion":19,"c_grupo":"4 ","c_id_practica":2860671174,"d_validacion":"SOLAPAMIENTO DE INTERNACIONES"}
,{"c_proceso":4821,"c_file_upload":3398291,"n_prestacion":770,"c_validacion":19,"c_grupo":"4 ","c_id_practica":2860679238,"d_validacion":"SOLAPAMIENTO DE INTERNACIONES"}
,{"c_proceso":4821,"c_file_upload":3398291,"n_prestacion":770,"c_validacion":19,"c_grupo":"4 ","c_id_practica":2860679054,"d_validacion":"SOLAPAMIENTO DE INTERNACIONES"}
,{"c_proceso":4821,"c_file_upload":3398291,"n_prestacion":770,"c_validacion":19,"c_grupo":"4 ","c_id_practica":2860682133,"d_validacion":"SOLAPAMIENTO DE INTERNACIONES"}
,{"c_proceso":4821,"c_file_upload":3398291,"n_prestacion":770,"c_validacion":19,"c_grupo":"4 ","c_id_practica":2860666272,"d_validacion":"SOLAPAMIENTO DE INTERNACIONES"}
,{"c_proceso":4821,"c_file_upload":3398291,"n_prestacion":769,"c_validacion":19,"c_grupo":"4 ","c_id_practica":2860668401,"d_validacion":"SOLAPAMIENTO DE INTERNACIONES"}
,{"c_proceso":4821,"c_file_upload":3398291,"n_prestacion":769,"c_validacion":19,"c_grupo":"4 ","c_id_practica":2860679611,"d_validacion":"SOLAPAMIENTO DE INTERNACIONES"}
,{"c_proceso":4821,"c_file_upload":3398291,"n_prestacion":769,"c_validacion":19,"c_grupo":"4 ","c_id_practica":2860668639,"d_validacion":"SOLAPAMIENTO DE INTERNACIONES"}
,{"c_proceso":4821,"c_file_upload":3398291,"n_prestacion":769,"c_validacion":19,"c_grupo":"4 ","c_id_practica":2860676483,"d_validacion":"SOLAPAMIENTO DE INTERNACIONES"}
,{"c_proceso":4821,"c_file_upload":3398291,"n_prestacion":769,"c_validacion":19,"c_grupo":"4 ","c_id_practica":2860671140,"d_validacion":"SOLAPAMIENTO DE INTERNACIONES"}
,{"c_proceso":4821,"c_file_upload":3398291,"n_prestacion":770,"c_validacion":19,"c_grupo":"4 ","c_id_practica":2860676434,"d_validacion":"SOLAPAMIENTO DE INTERNACIONES"}
,{"c_proceso":4821,"c_file_upload":3398291,"n_prestacion":770,"c_validacion":19,"c_grupo":"4 ","c_id_practica":2860676655,"d_validacion":"SOLAPAMIENTO DE INTERNACIONES"}
,{"c_proceso":4821,"c_file_upload":3398291,"n_prestacion":770,"c_validacion":19,"c_grupo":"4 ","c_id_practica":2860673932,"d_validacion":"SOLAPAMIENTO DE INTERNACIONES"}
,{"c_proceso":4821,"c_file_upload":3398291,"n_prestacion":770,"c_validacion":19,"c_grupo":"4 ","c_id_practica":2860668846,"d_validacion":"SOLAPAMIENTO DE INTERNACIONES"}
,{"c_proceso":4821,"c_file_upload":3398291,"n_prestacion":770,"c_validacion":19,"c_grupo":"4 ","c_id_practica":2860674251,"d_validacion":"SOLAPAMIENTO DE INTERNACIONES"}
,{"c_proceso":4821,"c_file_upload":3398291,"n_prestacion":770,"c_validacion":19,"c_grupo":"4 ","c_id_practica":2860665581,"d_validacion":"SOLAPAMIENTO DE INTERNACIONES"}
,{"c_proceso":4821,"c_file_upload":3398291,"n_prestacion":770,"c_validacion":19,"c_grupo":"4 ","c_id_practica":2860684123,"d_validacion":"SOLAPAMIENTO DE INTERNACIONES"}
,{"c_proceso":4821,"c_file_upload":3398291,"n_prestacion":770,"c_validacion":19,"c_grupo":"4 ","c_id_practica":2860679444,"d_validacion":"SOLAPAMIENTO DE INTERNACIONES"}
,{"c_proceso":4821,"c_file_upload":3398291,"n_prestacion":770,"c_validacion":19,"c_grupo":"4 ","c_id_practica":2860684544,"d_validacion":"SOLAPAMIENTO DE INTERNACIONES"}
,{"c_proceso":4821,"c_file_upload":3398291,"n_prestacion":770,"c_validacion":19,"c_grupo":"4 ","c_id_practica":2860681899,"d_validacion":"SOLAPAMIENTO DE INTERNACIONES"}
,{"c_proceso":4821,"c_file_upload":3398291,"n_prestacion":770,"c_validacion":19,"c_grupo":"4 ","c_id_practica":2860684237,"d_validacion":"SOLAPAMIENTO DE INTERNACIONES"}
,{"c_proceso":4821,"c_file_upload":3398291,"n_prestacion":770,"c_validacion":19,"c_grupo":"4 ","c_id_practica":2860668836,"d_validacion":"SOLAPAMIENTO DE INTERNACIONES"}
,{"c_proceso":4821,"c_file_upload":3398291,"n_prestacion":770,"c_validacion":19,"c_grupo":"4 ","c_id_practica":2860669149,"d_validacion":"SOLAPAMIENTO DE INTERNACIONES"}
,{"c_proceso":4821,"c_file_upload":3398291,"n_prestacion":770,"c_validacion":19,"c_grupo":"4 ","c_id_practica":2860679524,"d_validacion":"SOLAPAMIENTO DE INTERNACIONES"}
,{"c_proceso":4821,"c_file_upload":3398291,"n_prestacion":770,"c_validacion":19,"c_grupo":"4 ","c_id_practica":2860671814,"d_validacion":"SOLAPAMIENTO DE INTERNACIONES"}
,{"c_proceso":4821,"c_file_upload":3398291,"n_prestacion":770,"c_validacion":19,"c_grupo":"4 ","c_id_practica":2860678697,"d_validacion":"SOLAPAMIENTO DE INTERNACIONES"}
,{"c_proceso":4821,"c_file_upload":3398291,"n_prestacion":770,"c_validacion":23,"c_grupo":"5 ","c_id_practica":2860678697,"d_validacion":"PRACTICAS EXCLUYENTES"}
,{"c_proceso":4821,"c_file_upload":3398291,"n_prestacion":770,"c_validacion":19,"c_grupo":"4 ","c_id_practica":2860683693,"d_validacion":"SOLAPAMIENTO DE INTERNACIONES"}
,{"c_proceso":4821,"c_file_upload":3398291,"n_prestacion":770,"c_validacion":19,"c_grupo":"4 ","c_id_practica":2860684557,"d_validacion":"SOLAPAMIENTO DE INTERNACIONES"}
,{"c_proceso":4821,"c_file_upload":3398291,"n_prestacion":770,"c_validacion":19,"c_grupo":"4 ","c_id_practica":2860679163,"d_validacion":"SOLAPAMIENTO DE INTERNACIONES"}
,{"c_proceso":4821,"c_file_upload":3398291,"n_prestacion":770,"c_validacion":19,"c_grupo":"4 ","c_id_practica":2860676561,"d_validacion":"SOLAPAMIENTO DE INTERNACIONES"}
,{"c_proceso":4821,"c_file_upload":3398291,"n_prestacion":770,"c_validacion":19,"c_grupo":"4 ","c_id_practica":2860676823,"d_validacion":"SOLAPAMIENTO DE INTERNACIONES"}
,{"c_proceso":4821,"c_file_upload":3398291,"n_prestacion":770,"c_validacion":19,"c_grupo":"4 ","c_id_practica":2860670846,"d_validacion":"SOLAPAMIENTO DE INTERNACIONES"}
,{"c_proceso":4821,"c_file_upload":3398291,"n_prestacion":770,"c_validacion":19,"c_grupo":"4 ","c_id_practica":2860671413,"d_validacion":"SOLAPAMIENTO DE INTERNACIONES"}
,{"c_proceso":4821,"c_file_upload":3398291,"n_prestacion":770,"c_validacion":19,"c_grupo":"4 ","c_id_practica":2860676837,"d_validacion":"SOLAPAMIENTO DE INTERNACIONES"}
,{"c_proceso":4821,"c_file_upload":3398291,"n_prestacion":770,"c_validacion":19,"c_grupo":"4 ","c_id_practica":2860674226,"d_validacion":"SOLAPAMIENTO DE INTERNACIONES"}
,{"c_proceso":4821,"c_file_upload":3398291,"n_prestacion":770,"c_validacion":19,"c_grupo":"4 ","c_id_practica":2860679456,"d_validacion":"SOLAPAMIENTO DE INTERNACIONES"}
,{"c_proceso":4821,"c_file_upload":3398291,"n_prestacion":770,"c_validacion":19,"c_grupo":"4 ","c_id_practica":2860681978,"d_validacion":"SOLAPAMIENTO DE INTERNACIONES"}
,{"c_proceso":4821,"c_file_upload":3398291,"n_prestacion":770,"c_validacion":19,"c_grupo":"4 ","c_id_practica":2860679540,"d_validacion":"SOLAPAMIENTO DE INTERNACIONES"}
,{"c_proceso":4821,"c_file_upload":3398291,"n_prestacion":770,"c_validacion":19,"c_grupo":"4 ","c_id_practica":2860671514,"d_validacion":"SOLAPAMIENTO DE INTERNACIONES"}
,{"c_proceso":4821,"c_file_upload":3398291,"n_prestacion":770,"c_validacion":19,"c_grupo":"4 ","c_id_practica":2860671469,"d_validacion":"SOLAPAMIENTO DE INTERNACIONES"}
,{"c_proceso":4821,"c_file_upload":3398291,"n_prestacion":770,"c_validacion":19,"c_grupo":"4 ","c_id_practica":2860669123,"d_validacion":"SOLAPAMIENTO DE INTERNACIONES"}
,{"c_proceso":4821,"c_file_upload":3398291,"n_prestacion":770,"c_validacion":19,"c_grupo":"4 ","c_id_practica":2860671313,"d_validacion":"SOLAPAMIENTO DE INTERNACIONES"}
,{"c_proceso":4821,"c_file_upload":3398291,"n_prestacion":770,"c_validacion":19,"c_grupo":"4 ","c_id_practica":2860671459,"d_validacion":"SOLAPAMIENTO DE INTERNACIONES"}
,{"c_proceso":4821,"c_file_upload":3398291,"n_prestacion":770,"c_validacion":19,"c_grupo":"4 ","c_id_practica":2860669116,"d_validacion":"SOLAPAMIENTO DE INTERNACIONES"}
,{"c_proceso":4821,"c_file_upload":3398291,"n_prestacion":770,"c_validacion":19,"c_grupo":"4 ","c_id_practica":2860681889,"d_validacion":"SOLAPAMIENTO DE INTERNACIONES"}
,{"c_proceso":4821,"c_file_upload":3398291,"n_prestacion":770,"c_validacion":19,"c_grupo":"4 ","c_id_practica":2860681907,"d_validacion":"SOLAPAMIENTO DE INTERNACIONES"}
,{"c_proceso":4821,"c_file_upload":3398291,"n_prestacion":770,"c_validacion":19,"c_grupo":"4 ","c_id_practica":2860669185,"d_validacion":"SOLAPAMIENTO DE INTERNACIONES"}
,{"c_proceso":4821,"c_file_upload":3398291,"n_prestacion":770,"c_validacion":19,"c_grupo":"4 ","c_id_practica":2860665634,"d_validacion":"SOLAPAMIENTO DE INTERNACIONES"}
,{"c_proceso":4821,"c_file_upload":3398291,"n_prestacion":770,"c_validacion":19,"c_grupo":"4 ","c_id_practica":2860671171,"d_validacion":"SOLAPAMIENTO DE INTERNACIONES"}
,{"c_proceso":4821,"c_file_upload":3398291,"n_prestacion":770,"c_validacion":19,"c_grupo":"4 ","c_id_practica":2860684201,"d_validacion":"SOLAPAMIENTO DE INTERNACIONES"}
,{"c_proceso":4821,"c_file_upload":3398291,"n_prestacion":770,"c_validacion":19,"c_grupo":"4 ","c_id_practica":2860676379,"d_validacion":"SOLAPAMIENTO DE INTERNACIONES"}
,{"c_proceso":4821,"c_file_upload":3398291,"n_prestacion":770,"c_validacion":19,"c_grupo":"4 ","c_id_practica":2860674399,"d_validacion":"SOLAPAMIENTO DE INTERNACIONES"}
,{"c_proceso":4821,"c_file_upload":3398291,"n_prestacion":770,"c_validacion":19,"c_grupo":"4 ","c_id_practica":2860669005,"d_validacion":"SOLAPAMIENTO DE INTERNACIONES"}
,{"c_proceso":4821,"c_file_upload":3398291,"n_prestacion":769,"c_validacion":19,"c_grupo":"4 ","c_id_practica":2860681370,"d_validacion":"SOLAPAMIENTO DE INTERNACIONES"}
,{"c_proceso":4821,"c_file_upload":3398291,"n_prestacion":769,"c_validacion":19,"c_grupo":"4 ","c_id_practica":2860682095,"d_validacion":"SOLAPAMIENTO DE INTERNACIONES"}
,{"c_proceso":4821,"c_file_upload":3398291,"n_prestacion":769,"c_validacion":19,"c_grupo":"4 ","c_id_practica":2860673718,"d_validacion":"SOLAPAMIENTO DE INTERNACIONES"}
,{"c_proceso":4821,"c_file_upload":3398291,"n_prestacion":769,"c_validacion":19,"c_grupo":"4 ","c_id_practica":2860681122,"d_validacion":"SOLAPAMIENTO DE INTERNACIONES"}
,{"c_proceso":4821,"c_file_upload":3398291,"n_prestacion":769,"c_validacion":19,"c_grupo":"4 ","c_id_practica":2860684184,"d_validacion":"SOLAPAMIENTO DE INTERNACIONES"}
,{"c_proceso":4821,"c_file_upload":3398291,"n_prestacion":770,"c_validacion":19,"c_grupo":"4 ","c_id_practica":2860673790,"d_validacion":"SOLAPAMIENTO DE INTERNACIONES"}
,{"c_proceso":4821,"c_file_upload":3398291,"n_prestacion":770,"c_validacion":19,"c_grupo":"4 ","c_id_practica":2860678904,"d_validacion":"SOLAPAMIENTO DE INTERNACIONES"}
,{"c_proceso":4821,"c_file_upload":3398291,"n_prestacion":770,"c_validacion":19,"c_grupo":"4 ","c_id_practica":2860673679,"d_validacion":"SOLAPAMIENTO DE INTERNACIONES"}
,{"c_proceso":4821,"c_file_upload":3398291,"n_prestacion":770,"c_validacion":19,"c_grupo":"4 ","c_id_practica":2860666068,"d_validacion":"SOLAPAMIENTO DE INTERNACIONES"}
,{"c_proceso":4821,"c_file_upload":3398291,"n_prestacion":770,"c_validacion":19,"c_grupo":"4 ","c_id_practica":2860665894,"d_validacion":"SOLAPAMIENTO DE INTERNACIONES"}
,{"c_proceso":4821,"c_file_upload":3398291,"n_prestacion":770,"c_validacion":19,"c_grupo":"4 ","c_id_practica":2860684701,"d_validacion":"SOLAPAMIENTO DE INTERNACIONES"}
,{"c_proceso":4821,"c_file_upload":3398291,"n_prestacion":770,"c_validacion":19,"c_grupo":"4 ","c_id_practica":2860676729,"d_validacion":"SOLAPAMIENTO DE INTERNACIONES"}
,{"c_proceso":4821,"c_file_upload":3398291,"n_prestacion":769,"c_validacion":19,"c_grupo":"4 ","c_id_practica":2860684026,"d_validacion":"SOLAPAMIENTO DE INTERNACIONES"}
,{"c_proceso":4821,"c_file_upload":3398291,"n_prestacion":769,"c_validacion":19,"c_grupo":"4 ","c_id_practica":2860668743,"d_validacion":"SOLAPAMIENTO DE INTERNACIONES"}
,{"c_proceso":4821,"c_file_upload":3398291,"n_prestacion":769,"c_validacion":19,"c_grupo":"4 ","c_id_practica":2860676033,"d_validacion":"SOLAPAMIENTO DE INTERNACIONES"}
,{"c_proceso":4821,"c_file_upload":3398291,"n_prestacion":769,"c_validacion":19,"c_grupo":"4 ","c_id_practica":2860673656,"d_validacion":"SOLAPAMIENTO DE INTERNACIONES"}
,{"c_proceso":4821,"c_file_upload":3398291,"n_prestacion":769,"c_validacion":19,"c_grupo":"4 ","c_id_practica":2860674374,"d_validacion":"SOLAPAMIENTO DE INTERNACIONES"}
,{"c_proceso":4821,"c_file_upload":3398291,"n_prestacion":770,"c_validacion":19,"c_grupo":"4 ","c_id_practica":2860671027,"d_validacion":"SOLAPAMIENTO DE INTERNACIONES"}
,{"c_proceso":4821,"c_file_upload":3398291,"n_prestacion":770,"c_validacion":19,"c_grupo":"4 ","c_id_practica":2860665811,"d_validacion":"SOLAPAMIENTO DE INTERNACIONES"}
,{"c_proceso":4821,"c_file_upload":3398291,"n_prestacion":770,"c_validacion":19,"c_grupo":"4 ","c_id_practica":2860671394,"d_validacion":"SOLAPAMIENTO DE INTERNACIONES"}
,{"c_proceso":4821,"c_file_upload":3398291,"n_prestacion":770,"c_validacion":19,"c_grupo":"4 ","c_id_practica":2860668665,"d_validacion":"SOLAPAMIENTO DE INTERNACIONES"}
,{"c_proceso":4821,"c_file_upload":3398291,"n_prestacion":770,"c_validacion":19,"c_grupo":"4 ","c_id_practica":2860674396,"d_validacion":"SOLAPAMIENTO DE INTERNACIONES"}
,{"c_proceso":4821,"c_file_upload":3398291,"n_prestacion":769,"c_validacion":19,"c_grupo":"4 ","c_id_practica":2860677036,"d_validacion":"SOLAPAMIENTO DE INTERNACIONES"}
,{"c_proceso":4821,"c_file_upload":3398291,"n_prestacion":769,"c_validacion":19,"c_grupo":"4 ","c_id_practica":2860666049,"d_validacion":"SOLAPAMIENTO DE INTERNACIONES"}
,{"c_proceso":4821,"c_file_upload":3398291,"n_prestacion":769,"c_validacion":19,"c_grupo":"4 ","c_id_practica":2860668636,"d_validacion":"SOLAPAMIENTO DE INTERNACIONES"}
,{"c_proceso":4821,"c_file_upload":3398291,"n_prestacion":769,"c_validacion":19,"c_grupo":"4 ","c_id_practica":2860683754,"d_validacion":"SOLAPAMIENTO DE INTERNACIONES"}
,{"c_proceso":4821,"c_file_upload":3398291,"n_prestacion":769,"c_validacion":19,"c_grupo":"4 ","c_id_practica":2860676293,"d_validacion":"SOLAPAMIENTO DE INTERNACIONES"}
,{"c_proceso":4821,"c_file_upload":3398291,"n_prestacion":770,"c_validacion":19,"c_grupo":"4 ","c_id_practica":2860673552,"d_validacion":"SOLAPAMIENTO DE INTERNACIONES"}
,{"c_proceso":4821,"c_file_upload":3398291,"n_prestacion":770,"c_validacion":19,"c_grupo":"4 ","c_id_practica":2860671168,"d_validacion":"SOLAPAMIENTO DE INTERNACIONES"}
,{"c_proceso":4821,"c_file_upload":3398291,"n_prestacion":770,"c_validacion":19,"c_grupo":"4 ","c_id_practica":2860666065,"d_validacion":"SOLAPAMIENTO DE INTERNACIONES"}
,{"c_proceso":4821,"c_file_upload":3398291,"n_prestacion":770,"c_validacion":19,"c_grupo":"4 ","c_id_practica":2860679051,"d_validacion":"SOLAPAMIENTO DE INTERNACIONES"}
,{"c_proceso":4821,"c_file_upload":3398291,"n_prestacion":770,"c_validacion":19,"c_grupo":"4 ","c_id_practica":2860669284,"d_validacion":"SOLAPAMIENTO DE INTERNACIONES"}
,{"c_proceso":4821,"c_file_upload":3398291,"n_prestacion":769,"c_validacion":19,"c_grupo":"4 ","c_id_practica":2860673835,"d_validacion":"SOLAPAMIENTO DE INTERNACIONES"}
,{"c_proceso":4821,"c_file_upload":3398291,"n_prestacion":769,"c_validacion":19,"c_grupo":"4 ","c_id_practica":2860679608,"d_validacion":"SOLAPAMIENTO DE INTERNACIONES"}
,{"c_proceso":4821,"c_file_upload":3398291,"n_prestacion":769,"c_validacion":19,"c_grupo":"4 ","c_id_practica":2860678971,"d_validacion":"SOLAPAMIENTO DE INTERNACIONES"}
,{"c_proceso":4821,"c_file_upload":3398291,"n_prestacion":769,"c_validacion":19,"c_grupo":"4 ","c_id_practica":2860678753,"d_validacion":"SOLAPAMIENTO DE INTERNACIONES"}
,{"c_proceso":4821,"c_file_upload":3398291,"n_prestacion":769,"c_validacion":19,"c_grupo":"4 ","c_id_practica":2860681433,"d_validacion":"SOLAPAMIENTO DE INTERNACIONES"}
,{"c_proceso":4821,"c_file_upload":3398291,"n_prestacion":770,"c_validacion":19,"c_grupo":"4 ","c_id_practica":2860683879,"d_validacion":"SOLAPAMIENTO DE INTERNACIONES"}
,{"c_proceso":4821,"c_file_upload":3398291,"n_prestacion":770,"c_validacion":19,"c_grupo":"4 ","c_id_practica":2860681393,"d_validacion":"SOLAPAMIENTO DE INTERNACIONES"}
,{"c_proceso":4821,"c_file_upload":3398291,"n_prestacion":770,"c_validacion":19,"c_grupo":"4 ","c_id_practica":2860681557,"d_validacion":"SOLAPAMIENTO DE INTERNACIONES"}
,{"c_proceso":4821,"c_file_upload":3398291,"n_prestacion":770,"c_validacion":19,"c_grupo":"4 ","c_id_practica":2860665891,"d_validacion":"SOLAPAMIENTO DE INTERNACIONES"}
,{"c_proceso":4821,"c_file_upload":3398291,"n_prestacion":770,"c_validacion":19,"c_grupo":"4 ","c_id_practica":2860682129,"d_validacion":"SOLAPAMIENTO DE INTERNACIONES"}
,{"c_proceso":4821,"c_file_upload":3398291,"n_prestacion":769,"c_validacion":19,"c_grupo":"4 ","c_id_practica":2860679203,"d_validacion":"SOLAPAMIENTO DE INTERNACIONES"}
,{"c_proceso":4821,"c_file_upload":3398291,"n_prestacion":769,"c_validacion":19,"c_grupo":"4 ","c_id_practica":2860683751,"d_validacion":"SOLAPAMIENTO DE INTERNACIONES"}
,{"c_proceso":4821,"c_file_upload":3398291,"n_prestacion":769,"c_validacion":19,"c_grupo":"4 ","c_id_practica":2860668581,"d_validacion":"SOLAPAMIENTO DE INTERNACIONES"}
,{"c_proceso":4821,"c_file_upload":3398291,"n_prestacion":769,"c_validacion":19,"c_grupo":"4 ","c_id_practica":2860668633,"d_validacion":"SOLAPAMIENTO DE INTERNACIONES"}
,{"c_proceso":4821,"c_file_upload":3398291,"n_prestacion":769,"c_validacion":19,"c_grupo":"4 ","c_id_practica":2860682093,"d_validacion":"SOLAPAMIENTO DE INTERNACIONES"}
,{"c_proceso":4821,"c_file_upload":3398291,"n_prestacion":770,"c_validacion":19,"c_grupo":"4 ","c_id_practica":2860681273,"d_validacion":"SOLAPAMIENTO DE INTERNACIONES"}
,{"c_proceso":4821,"c_file_upload":3398291,"n_prestacion":770,"c_validacion":19,"c_grupo":"4 ","c_id_practica":2860668596,"d_validacion":"SOLAPAMIENTO DE INTERNACIONES"}
,{"c_proceso":4821,"c_file_upload":3398291,"n_prestacion":770,"c_validacion":19,"c_grupo":"4 ","c_id_practica":2860671391,"d_validacion":"SOLAPAMIENTO DE INTERNACIONES"}
,{"c_proceso":4821,"c_file_upload":3398291,"n_prestacion":770,"c_validacion":19,"c_grupo":"4 ","c_id_practica":2860668663,"d_validacion":"SOLAPAMIENTO DE INTERNACIONES"}
,{"c_proceso":4821,"c_file_upload":3398291,"n_prestacion":770,"c_validacion":19,"c_grupo":"4 ","c_id_practica":2860684698,"d_validacion":"SOLAPAMIENTO DE INTERNACIONES"}
,{"c_proceso":4821,"c_file_upload":3398291,"n_prestacion":769,"c_validacion":19,"c_grupo":"4 ","c_id_practica":2860677034,"d_validacion":"SOLAPAMIENTO DE INTERNACIONES"}
,{"c_proceso":4821,"c_file_upload":3398291,"n_prestacion":769,"c_validacion":19,"c_grupo":"4 ","c_id_practica":2860676030,"d_validacion":"SOLAPAMIENTO DE INTERNACIONES"}
,{"c_proceso":4821,"c_file_upload":3398291,"n_prestacion":769,"c_validacion":19,"c_grupo":"4 ","c_id_practica":2860684181,"d_validacion":"SOLAPAMIENTO DE INTERNACIONES"}
,{"c_proceso":4821,"c_file_upload":3398291,"n_prestacion":769,"c_validacion":19,"c_grupo":"4 ","c_id_practica":2860673652,"d_validacion":"SOLAPAMIENTO DE INTERNACIONES"}
,{"c_proceso":4821,"c_file_upload":3398291,"n_prestacion":769,"c_validacion":19,"c_grupo":"4 ","c_id_practica":2860671225,"d_validacion":"SOLAPAMIENTO DE INTERNACIONES"}
,{"c_proceso":4821,"c_file_upload":3398291,"n_prestacion":769,"c_validacion":19,"c_grupo":"4 ","c_id_practica":2860668467,"d_validacion":"SOLAPAMIENTO DE INTERNACIONES"}
,{"c_proceso":4821,"c_file_upload":3398291,"n_prestacion":769,"c_validacion":19,"c_grupo":"4 ","c_id_practica":2860682089,"d_validacion":"SOLAPAMIENTO DE INTERNACIONES"}
,{"c_proceso":4821,"c_file_upload":3398291,"n_prestacion":769,"c_validacion":19,"c_grupo":"4 ","c_id_practica":2860673416,"d_validacion":"SOLAPAMIENTO DE INTERNACIONES"}
,{"c_proceso":4821,"c_file_upload":3398291,"n_prestacion":769,"c_validacion":19,"c_grupo":"4 ","c_id_practica":2860676289,"d_validacion":"SOLAPAMIENTO DE INTERNACIONES"}
,{"c_proceso":4821,"c_file_upload":3398291,"n_prestacion":769,"c_validacion":19,"c_grupo":"4 ","c_id_practica":2860668741,"d_validacion":"SOLAPAMIENTO DE INTERNACIONES"}
,{"c_proceso":4821,"c_file_upload":3398291,"n_prestacion":769,"c_validacion":19,"c_grupo":"4 ","c_id_practica":2860676169,"d_validacion":"SOLAPAMIENTO DE INTERNACIONES"}
,{"c_proceso":4821,"c_file_upload":3398291,"n_prestacion":769,"c_validacion":19,"c_grupo":"4 ","c_id_practica":2860681117,"d_validacion":"SOLAPAMIENTO DE INTERNACIONES"}
,{"c_proceso":4821,"c_file_upload":3398291,"n_prestacion":769,"c_validacion":19,"c_grupo":"4 ","c_id_practica":2860679605,"d_validacion":"SOLAPAMIENTO DE INTERNACIONES"}
,{"c_proceso":4821,"c_file_upload":3398291,"n_prestacion":769,"c_validacion":19,"c_grupo":"4 ","c_id_practica":2860668738,"d_validacion":"SOLAPAMIENTO DE INTERNACIONES"}
,{"c_proceso":4821,"c_file_upload":3398291,"n_prestacion":769,"c_validacion":19,"c_grupo":"4 ","c_id_practica":2860668579,"d_validacion":"SOLAPAMIENTO DE INTERNACIONES"}
,{"c_proceso":4821,"c_file_upload":3398291,"n_prestacion":769,"c_validacion":19,"c_grupo":"4 ","c_id_practica":2860671137,"d_validacion":"SOLAPAMIENTO DE INTERNACIONES"}
,{"c_proceso":4821,"c_file_upload":3398291,"n_prestacion":769,"c_validacion":19,"c_grupo":"4 ","c_id_practica":2860678749,"d_validacion":"SOLAPAMIENTO DE INTERNACIONES"}
,{"c_proceso":4821,"c_file_upload":3398291,"n_prestacion":769,"c_validacion":19,"c_grupo":"4 ","c_id_practica":2860673535,"d_validacion":"SOLAPAMIENTO DE INTERNACIONES"}
,{"c_proceso":4821,"c_file_upload":3398291,"n_prestacion":769,"c_validacion":19,"c_grupo":"4 ","c_id_practica":2860671911,"d_validacion":"SOLAPAMIENTO DE INTERNACIONES"}
,{"c_proceso":4821,"c_file_upload":3398291,"n_prestacion":769,"c_validacion":19,"c_grupo":"4 ","c_id_practica":2860684178,"d_validacion":"SOLAPAMIENTO DE INTERNACIONES"}
,{"c_proceso":4821,"c_file_upload":3398291,"n_prestacion":769,"c_validacion":19,"c_grupo":"4 ","c_id_practica":2860670884,"d_validacion":"SOLAPAMIENTO DE INTERNACIONES"}
,{"c_proceso":4821,"c_file_upload":3398291,"n_prestacion":769,"c_validacion":19,"c_grupo":"4 ","c_id_practica":2860676286,"d_validacion":"SOLAPAMIENTO DE INTERNACIONES"}
,{"c_proceso":4821,"c_file_upload":3398291,"n_prestacion":769,"c_validacion":19,"c_grupo":"4 ","c_id_practica":2860668465,"d_validacion":"SOLAPAMIENTO DE INTERNACIONES"}
,{"c_proceso":4821,"c_file_upload":3398291,"n_prestacion":769,"c_validacion":19,"c_grupo":"4 ","c_id_practica":2860684174,"d_validacion":"SOLAPAMIENTO DE INTERNACIONES"}
,{"c_proceso":4821,"c_file_upload":3398291,"n_prestacion":769,"c_validacion":19,"c_grupo":"4 ","c_id_practica":2860682087,"d_validacion":"SOLAPAMIENTO DE INTERNACIONES"}
,{"c_proceso":4821,"c_file_upload":3398291,"n_prestacion":769,"c_validacion":19,"c_grupo":"4 ","c_id_practica":2860673414,"d_validacion":"SOLAPAMIENTO DE INTERNACIONES"}
,{"c_proceso":4821,"c_file_upload":3398291,"n_prestacion":769,"c_validacion":19,"c_grupo":"4 ","c_id_practica":2860671376,"d_validacion":"SOLAPAMIENTO DE INTERNACIONES"}
,{"c_proceso":4821,"c_file_upload":3398291,"n_prestacion":769,"c_validacion":19,"c_grupo":"4 ","c_id_practica":2860671021,"d_validacion":"SOLAPAMIENTO DE INTERNACIONES"}
,{"c_proceso":4821,"c_file_upload":3398291,"n_prestacion":769,"c_validacion":19,"c_grupo":"4 ","c_id_practica":2860669253,"d_validacion":"SOLAPAMIENTO DE INTERNACIONES"}
,{"c_proceso":4821,"c_file_upload":3398291,"n_prestacion":769,"c_validacion":19,"c_grupo":"4 ","c_id_practica":2860683949,"d_validacion":"SOLAPAMIENTO DE INTERNACIONES"}
,{"c_proceso":4821,"c_file_upload":3398291,"n_prestacion":769,"c_validacion":19,"c_grupo":"4 ","c_id_practica":2860678884,"d_validacion":"SOLAPAMIENTO DE INTERNACIONES"}
,{"c_proceso":4821,"c_file_upload":3398291,"n_prestacion":769,"c_validacion":19,"c_grupo":"4 ","c_id_practica":2860671908,"d_validacion":"SOLAPAMIENTO DE INTERNACIONES"}
,{"c_proceso":4821,"c_file_upload":3398291,"n_prestacion":769,"c_validacion":19,"c_grupo":"4 ","c_id_practica":2860681367,"d_validacion":"SOLAPAMIENTO DE INTERNACIONES"}
,{"c_proceso":4821,"c_file_upload":3398291,"n_prestacion":769,"c_validacion":19,"c_grupo":"4 ","c_id_practica":2860676027,"d_validacion":"SOLAPAMIENTO DE INTERNACIONES"}
,{"c_proceso":4821,"c_file_upload":3398291,"n_prestacion":769,"c_validacion":19,"c_grupo":"4 ","c_id_practica":2860668734,"d_validacion":"SOLAPAMIENTO DE INTERNACIONES"}
,{"c_proceso":4821,"c_file_upload":3398291,"n_prestacion":769,"c_validacion":19,"c_grupo":"4 ","c_id_practica":2860671372,"d_validacion":"SOLAPAMIENTO DE INTERNACIONES"}
,{"c_proceso":4821,"c_file_upload":3398291,"n_prestacion":769,"c_validacion":19,"c_grupo":"4 ","c_id_practica":2860671905,"d_validacion":"SOLAPAMIENTO DE INTERNACIONES"}
,{"c_proceso":4821,"c_file_upload":3398291,"n_prestacion":769,"c_validacion":19,"c_grupo":"4 ","c_id_practica":2860668577,"d_validacion":"SOLAPAMIENTO DE INTERNACIONES"}
,{"c_proceso":4821,"c_file_upload":3398291,"n_prestacion":769,"c_validacion":19,"c_grupo":"4 ","c_id_practica":2860683863,"d_validacion":"SOLAPAMIENTO DE INTERNACIONES"}
,{"c_proceso":4821,"c_file_upload":3398291,"n_prestacion":769,"c_validacion":19,"c_grupo":"4 ","c_id_practica":2860668398,"d_validacion":"SOLAPAMIENTO DE INTERNACIONES"}
,{"c_proceso":4821,"c_file_upload":3398291,"n_prestacion":769,"c_validacion":19,"c_grupo":"4 ","c_id_practica":2860671369,"d_validacion":"SOLAPAMIENTO DE INTERNACIONES"}
,{"c_proceso":4821,"c_file_upload":3398291,"n_prestacion":769,"c_validacion":19,"c_grupo":"4 ","c_id_practica":2860677031,"d_validacion":"SOLAPAMIENTO DE INTERNACIONES"}
,{"c_proceso":4821,"c_file_upload":3398291,"n_prestacion":769,"c_validacion":19,"c_grupo":"4 ","c_id_practica":2860673649,"d_validacion":"SOLAPAMIENTO DE INTERNACIONES"}
,{"c_proceso":4821,"c_file_upload":3398291,"n_prestacion":769,"c_validacion":19,"c_grupo":"4 ","c_id_practica":2860676023,"d_validacion":"SOLAPAMIENTO DE INTERNACIONES"}
,{"c_proceso":4821,"c_file_upload":3398291,"n_prestacion":769,"c_validacion":19,"c_grupo":"4 ","c_id_practica":2860671231,"d_validacion":"SOLAPAMIENTO DE INTERNACIONES"}
,{"c_proceso":4821,"c_file_upload":3398291,"n_prestacion":769,"c_validacion":19,"c_grupo":"4 ","c_id_practica":2860668395,"d_validacion":"SOLAPAMIENTO DE INTERNACIONES"}
,{"c_proceso":4821,"c_file_upload":3398291,"n_prestacion":769,"c_validacion":19,"c_grupo":"4 ","c_id_practica":2860676363,"d_validacion":"SOLAPAMIENTO DE INTERNACIONES"}
,{"c_proceso":4821,"c_file_upload":3398291,"n_prestacion":769,"c_validacion":19,"c_grupo":"4 ","c_id_practica":2860673647,"d_validacion":"SOLAPAMIENTO DE INTERNACIONES"}
,{"c_proceso":4821,"c_file_upload":3398291,"n_prestacion":769,"c_validacion":19,"c_grupo":"4 ","c_id_practica":2860677028,"d_validacion":"SOLAPAMIENTO DE INTERNACIONES"}
,{"c_proceso":4821,"c_file_upload":3398291,"n_prestacion":769,"c_validacion":19,"c_grupo":"4 ","c_id_practica":2860671367,"d_validacion":"SOLAPAMIENTO DE INTERNACIONES"}
,{"c_proceso":4821,"c_file_upload":3398291,"n_prestacion":769,"c_validacion":19,"c_grupo":"4 ","c_id_practica":2860665854,"d_validacion":"SOLAPAMIENTO DE INTERNACIONES"}
,{"c_proceso":4821,"c_file_upload":3398291,"n_prestacion":769,"c_validacion":19,"c_grupo":"4 ","c_id_practica":2860670881,"d_validacion":"SOLAPAMIENTO DE INTERNACIONES"}
,{"c_proceso":4821,"c_file_upload":3398291,"n_prestacion":769,"c_validacion":19,"c_grupo":"4 ","c_id_practica":2860684681,"d_validacion":"SOLAPAMIENTO DE INTERNACIONES"}
,{"c_proceso":4821,"c_file_upload":3398291,"n_prestacion":769,"c_validacion":19,"c_grupo":"4 ","c_id_practica":2860665793,"d_validacion":"SOLAPAMIENTO DE INTERNACIONES"}
,{"c_proceso":4821,"c_file_upload":3398291,"n_prestacion":769,"c_validacion":19,"c_grupo":"4 ","c_id_practica":2860671365,"d_validacion":"SOLAPAMIENTO DE INTERNACIONES"}
,{"c_proceso":4821,"c_file_upload":3398291,"n_prestacion":769,"c_validacion":19,"c_grupo":"4 ","c_id_practica":2860668574,"d_validacion":"SOLAPAMIENTO DE INTERNACIONES"}
,{"c_proceso":4821,"c_file_upload":3398291,"n_prestacion":769,"c_validacion":19,"c_grupo":"4 ","c_id_practica":2860668392,"d_validacion":"SOLAPAMIENTO DE INTERNACIONES"}
,{"c_proceso":4821,"c_file_upload":3398291,"n_prestacion":769,"c_validacion":19,"c_grupo":"4 ","c_id_practica":2860676480,"d_validacion":"SOLAPAMIENTO DE INTERNACIONES"}
,{"c_proceso":4821,"c_file_upload":3398291,"n_prestacion":769,"c_validacion":19,"c_grupo":"4 ","c_id_practica":2860684678,"d_validacion":"SOLAPAMIENTO DE INTERNACIONES"}
,{"c_proceso":4821,"c_file_upload":3398291,"n_prestacion":769,"c_validacion":19,"c_grupo":"4 ","c_id_practica":2860668647,"d_validacion":"SOLAPAMIENTO DE INTERNACIONES"}
,{"c_proceso":4821,"c_file_upload":3398291,"n_prestacion":769,"c_validacion":19,"c_grupo":"4 ","c_id_practica":2860677025,"d_validacion":"SOLAPAMIENTO DE INTERNACIONES"}
,{"c_proceso":4821,"c_file_upload":3398291,"n_prestacion":769,"c_validacion":19,"c_grupo":"4 ","c_id_practica":2860676283,"d_validacion":"SOLAPAMIENTO DE INTERNACIONES"}
,{"c_proceso":4821,"c_file_upload":3398291,"n_prestacion":769,"c_validacion":19,"c_grupo":"4 ","c_id_practica":2860668645,"d_validacion":"SOLAPAMIENTO DE INTERNACIONES"}
,{"c_proceso":4821,"c_file_upload":3398291,"n_prestacion":769,"c_validacion":19,"c_grupo":"4 ","c_id_practica":2860678746,"d_validacion":"SOLAPAMIENTO DE INTERNACIONES"}
,{"c_proceso":4821,"c_file_upload":3398291,"n_prestacion":769,"c_validacion":19,"c_grupo":"4 ","c_id_practica":2860668731,"d_validacion":"SOLAPAMIENTO DE INTERNACIONES"}
,{"c_proceso":4821,"c_file_upload":3398291,"n_prestacion":769,"c_validacion":19,"c_grupo":"4 ","c_id_practica":2860668389,"d_validacion":"SOLAPAMIENTO DE INTERNACIONES"}
,{"c_proceso":4821,"c_file_upload":3398291,"n_prestacion":769,"c_validacion":19,"c_grupo":"4 ","c_id_practica":2860677023,"d_validacion":"SOLAPAMIENTO DE INTERNACIONES"}
,{"c_proceso":4821,"c_file_upload":3398291,"n_prestacion":769,"c_validacion":19,"c_grupo":"4 ","c_id_practica":2860683947,"d_validacion":"SOLAPAMIENTO DE INTERNACIONES"}
,{"c_proceso":4821,"c_file_upload":3398291,"n_prestacion":769,"c_validacion":19,"c_grupo":"4 ","c_id_practica":2860671228,"d_validacion":"SOLAPAMIENTO DE INTERNACIONES"}
,{"c_proceso":4821,"c_file_upload":3398291,"n_prestacion":769,"c_validacion":19,"c_grupo":"4 ","c_id_practica":2860684171,"d_validacion":"SOLAPAMIENTO DE INTERNACIONES"}
,{"c_proceso":4821,"c_file_upload":3398291,"n_prestacion":769,"c_validacion":19,"c_grupo":"4 ","c_id_practica":2860676279,"d_validacion":"SOLAPAMIENTO DE INTERNACIONES"}
,{"c_proceso":4821,"c_file_upload":3398291,"n_prestacion":769,"c_validacion":19,"c_grupo":"4 ","c_id_practica":2860671363,"d_validacion":"SOLAPAMIENTO DE INTERNACIONES"}
,{"c_proceso":4821,"c_file_upload":3398291,"n_prestacion":769,"c_validacion":19,"c_grupo":"4 ","c_id_practica":2860676359,"d_validacion":"SOLAPAMIENTO DE INTERNACIONES"}
,{"c_proceso":4821,"c_file_upload":3398291,"n_prestacion":769,"c_validacion":19,"c_grupo":"4 ","c_id_practica":2860684675,"d_validacion":"SOLAPAMIENTO DE INTERNACIONES"}
,{"c_proceso":4821,"c_file_upload":3398291,"n_prestacion":769,"c_validacion":19,"c_grupo":"4 ","c_id_practica":2860668386,"d_validacion":"SOLAPAMIENTO DE INTERNACIONES"}
,{"c_proceso":4821,"c_file_upload":3398291,"n_prestacion":769,"c_validacion":19,"c_grupo":"4 ","c_id_practica":2860681114,"d_validacion":"SOLAPAMIENTO DE INTERNACIONES"}
,{"c_proceso":4821,"c_file_upload":3398291,"n_prestacion":769,"c_validacion":19,"c_grupo":"4 ","c_id_practica":2860681439,"d_validacion":"SOLAPAMIENTO DE INTERNACIONES"}
,{"c_proceso":4821,"c_file_upload":3398291,"n_prestacion":769,"c_validacion":19,"c_grupo":"4 ","c_id_practica":2860668571,"d_validacion":"SOLAPAMIENTO DE INTERNACIONES"}
,{"c_proceso":4821,"c_file_upload":3398291,"n_prestacion":769,"c_validacion":19,"c_grupo":"4 ","c_id_practica":2860671902,"d_validacion":"SOLAPAMIENTO DE INTERNACIONES"}
,{"c_proceso":4821,"c_file_upload":3398291,"n_prestacion":769,"c_validacion":19,"c_grupo":"4 ","c_id_practica":2860676477,"d_validacion":"SOLAPAMIENTO DE INTERNACIONES"}
,{"c_proceso":4821,"c_file_upload":3398291,"n_prestacion":680,"c_validacion":19,"c_grupo":"4 ","c_id_practica":2860666586,"d_validacion":"SOLAPAMIENTO DE INTERNACIONES"}
,{"c_proceso":4821,"c_file_upload":3398291,"n_prestacion":680,"c_validacion":19,"c_grupo":"4 ","c_id_practica":2860678725,"d_validacion":"SOLAPAMIENTO DE INTERNACIONES"}
,{"c_proceso":4821,"c_file_upload":3398291,"n_prestacion":680,"c_validacion":19,"c_grupo":"4 ","c_id_practica":2860681333,"d_validacion":"SOLAPAMIENTO DE INTERNACIONES"}
,{"c_proceso":4821,"c_file_upload":3398291,"n_prestacion":680,"c_validacion":19,"c_grupo":"4 ","c_id_practica":2860676446,"d_validacion":"SOLAPAMIENTO DE INTERNACIONES"}
,{"c_proceso":4821,"c_file_upload":3398291,"n_prestacion":680,"c_validacion":19,"c_grupo":"4 ","c_id_practica":2860673999,"d_validacion":"SOLAPAMIENTO DE INTERNACIONES"}
,{"c_proceso":4821,"c_file_upload":3398291,"n_prestacion":680,"c_validacion":19,"c_grupo":"4 ","c_id_practica":2860684417,"d_validacion":"SOLAPAMIENTO DE INTERNACIONES"}
,{"c_proceso":4821,"c_file_upload":3398291,"n_prestacion":680,"c_validacion":19,"c_grupo":"4 ","c_id_practica":2860683833,"d_validacion":"SOLAPAMIENTO DE INTERNACIONES"}
,{"c_proceso":4821,"c_file_upload":3398291,"n_prestacion":680,"c_validacion":19,"c_grupo":"4 ","c_id_practica":2860671300,"d_validacion":"SOLAPAMIENTO DE INTERNACIONES"}
,{"c_proceso":4821,"c_file_upload":3398291,"n_prestacion":680,"c_validacion":19,"c_grupo":"4 ","c_id_practica":2860674079,"d_validacion":"SOLAPAMIENTO DE INTERNACIONES"}
,{"c_proceso":4821,"c_file_upload":3398291,"n_prestacion":680,"c_validacion":19,"c_grupo":"4 ","c_id_practica":2860681853,"d_validacion":"SOLAPAMIENTO DE INTERNACIONES"}
,{"c_proceso":4821,"c_file_upload":3398291,"n_prestacion":769,"c_validacion":19,"c_grupo":"4 ","c_id_practica":2860666640,"d_validacion":"SOLAPAMIENTO DE INTERNACIONES"}
,{"c_proceso":4821,"c_file_upload":3398291,"n_prestacion":769,"c_validacion":19,"c_grupo":"4 ","c_id_practica":2860673644,"d_validacion":"SOLAPAMIENTO DE INTERNACIONES"}
,{"c_proceso":4821,"c_file_upload":3398291,"n_prestacion":769,"c_validacion":19,"c_grupo":"4 ","c_id_practica":2860683748,"d_validacion":"SOLAPAMIENTO DE INTERNACIONES"}
,{"c_proceso":4821,"c_file_upload":3398291,"n_prestacion":769,"c_validacion":19,"c_grupo":"4 ","c_id_practica":2860684035,"d_validacion":"SOLAPAMIENTO DE INTERNACIONES"}
,{"c_proceso":4821,"c_file_upload":3398291,"n_prestacion":769,"c_validacion":19,"c_grupo":"4 ","c_id_practica":2860676474,"d_validacion":"SOLAPAMIENTO DE INTERNACIONES"}
,{"c_proceso":4821,"c_file_upload":3398291,"n_prestacion":769,"c_validacion":19,"c_grupo":"4 ","c_id_practica":2860684186,"d_validacion":"SOLAPAMIENTO DE INTERNACIONES"}
,{"c_proceso":4821,"c_file_upload":3398291,"n_prestacion":769,"c_validacion":19,"c_grupo":"4 ","c_id_practica":2860671147,"d_validacion":"SOLAPAMIENTO DE INTERNACIONES"}
,{"c_proceso":4821,"c_file_upload":3398291,"n_prestacion":769,"c_validacion":19,"c_grupo":"4 ","c_id_practica":2860681436,"d_validacion":"SOLAPAMIENTO DE INTERNACIONES"}
,{"c_proceso":4821,"c_file_upload":3398291,"n_prestacion":769,"c_validacion":19,"c_grupo":"4 ","c_id_practica":2860682084,"d_validacion":"SOLAPAMIENTO DE INTERNACIONES"}
,{"c_proceso":4821,"c_file_upload":3398291,"n_prestacion":769,"c_validacion":19,"c_grupo":"4 ","c_id_practica":2860668411,"d_validacion":"SOLAPAMIENTO DE INTERNACIONES"}
,{"c_proceso":4821,"c_file_upload":3398291,"n_prestacion":680,"c_validacion":23,"c_grupo":"5 ","c_id_practica":2860681208,"d_validacion":"PRACTICAS EXCLUYENTES"}
,{"c_proceso":4821,"c_file_upload":3398291,"n_prestacion":770,"c_validacion":19,"c_grupo":"4 ","c_id_practica":2860682197,"d_validacion":"SOLAPAMIENTO DE INTERNACIONES"}
,{"c_proceso":4821,"c_file_upload":3398291,"n_prestacion":770,"c_validacion":19,"c_grupo":"4 ","c_id_practica":2860672066,"d_validacion":"SOLAPAMIENTO DE INTERNACIONES"}
,{"c_proceso":4821,"c_file_upload":3398291,"n_prestacion":770,"c_validacion":19,"c_grupo":"4 ","c_id_practica":2860672928,"d_validacion":"SOLAPAMIENTO DE INTERNACIONES"}
,{"c_proceso":4821,"c_file_upload":3398291,"n_prestacion":770,"c_validacion":19,"c_grupo":"4 ","c_id_practica":2860676043,"d_validacion":"SOLAPAMIENTO DE INTERNACIONES"}
,{"c_proceso":4821,"c_file_upload":3398291,"n_prestacion":770,"c_validacion":19,"c_grupo":"4 ","c_id_practica":2860670829,"d_validacion":"SOLAPAMIENTO DE INTERNACIONES"}
,{"c_proceso":4821,"c_file_upload":3398291,"n_prestacion":770,"c_validacion":19,"c_grupo":"4 ","c_id_practica":2860684626,"d_validacion":"SOLAPAMIENTO DE INTERNACIONES"}
,{"c_proceso":4821,"c_file_upload":3398291,"n_prestacion":769,"c_validacion":19,"c_grupo":"4 ","c_id_practica":2860682163,"d_validacion":"SOLAPAMIENTO DE INTERNACIONES"}
,{"c_proceso":4821,"c_file_upload":3398291,"n_prestacion":769,"c_validacion":19,"c_grupo":"4 ","c_id_practica":2860679906,"d_validacion":"SOLAPAMIENTO DE INTERNACIONES"}
,{"c_proceso":4821,"c_file_upload":3398291,"n_prestacion":769,"c_validacion":19,"c_grupo":"4 ","c_id_practica":2860677074,"d_validacion":"SOLAPAMIENTO DE INTERNACIONES"}
,{"c_proceso":4821,"c_file_upload":3398291,"n_prestacion":769,"c_validacion":19,"c_grupo":"4 ","c_id_practica":2860667046,"d_validacion":"SOLAPAMIENTO DE INTERNACIONES"}
,{"c_proceso":4821,"c_file_upload":3398291,"n_prestacion":770,"c_validacion":19,"c_grupo":"4 ","c_id_practica":2860666527,"d_validacion":"SOLAPAMIENTO DE INTERNACIONES"}
,{"c_proceso":4821,"c_file_upload":3398291,"n_prestacion":770,"c_validacion":19,"c_grupo":"4 ","c_id_practica":2860669327,"d_validacion":"SOLAPAMIENTO DE INTERNACIONES"}
,{"c_proceso":4821,"c_file_upload":3398291,"n_prestacion":770,"c_validacion":19,"c_grupo":"4 ","c_id_practica":2860669411,"d_validacion":"SOLAPAMIENTO DE INTERNACIONES"}
,{"c_proceso":4821,"c_file_upload":3398291,"n_prestacion":770,"c_validacion":19,"c_grupo":"4 ","c_id_practica":2860666941,"d_validacion":"SOLAPAMIENTO DE INTERNACIONES"}
,{"c_proceso":4821,"c_file_upload":3398291,"n_prestacion":769,"c_validacion":19,"c_grupo":"4 ","c_id_practica":2860671956,"d_validacion":"SOLAPAMIENTO DE INTERNACIONES"}
,{"c_proceso":4821,"c_file_upload":3398291,"n_prestacion":769,"c_validacion":19,"c_grupo":"4 ","c_id_practica":2860672198,"d_validacion":"SOLAPAMIENTO DE INTERNACIONES"}
,{"c_proceso":4821,"c_file_upload":3398291,"n_prestacion":770,"c_validacion":19,"c_grupo":"4 ","c_id_practica":2860684761,"d_validacion":"SOLAPAMIENTO DE INTERNACIONES"}
,{"c_proceso":4821,"c_file_upload":3398291,"n_prestacion":770,"c_validacion":19,"c_grupo":"4 ","c_id_practica":2860674565,"d_validacion":"SOLAPAMIENTO DE INTERNACIONES"}
,{"c_proceso":4821,"c_file_upload":3398291,"n_prestacion":770,"c_validacion":19,"c_grupo":"4 ","c_id_practica":2860684961,"d_validacion":"SOLAPAMIENTO DE INTERNACIONES"}
,{"c_proceso":4821,"c_file_upload":3398291,"n_prestacion":769,"c_validacion":19,"c_grupo":"4 ","c_id_practica":2860682160,"d_validacion":"SOLAPAMIENTO DE INTERNACIONES"}
,{"c_proceso":4821,"c_file_upload":3398291,"n_prestacion":769,"c_validacion":19,"c_grupo":"4 ","c_id_practica":2860685068,"d_validacion":"SOLAPAMIENTO DE INTERNACIONES"}
,{"c_proceso":4821,"c_file_upload":3398291,"n_prestacion":770,"c_validacion":19,"c_grupo":"4 ","c_id_practica":2860679695,"d_validacion":"SOLAPAMIENTO DE INTERNACIONES"}
,{"c_proceso":4821,"c_file_upload":3398291,"n_prestacion":770,"c_validacion":19,"c_grupo":"4 ","c_id_practica":2860677241,"d_validacion":"SOLAPAMIENTO DE INTERNACIONES"}
,{"c_proceso":4821,"c_file_upload":3398291,"n_prestacion":770,"c_validacion":19,"c_grupo":"4 ","c_id_practica":2860674683,"d_validacion":"SOLAPAMIENTO DE INTERNACIONES"}
,{"c_proceso":4821,"c_file_upload":3398291,"n_prestacion":769,"c_validacion":19,"c_grupo":"4 ","c_id_practica":2860674424,"d_validacion":"SOLAPAMIENTO DE INTERNACIONES"}
,{"c_proceso":4821,"c_file_upload":3398291,"n_prestacion":769,"c_validacion":19,"c_grupo":"4 ","c_id_practica":2860677406,"d_validacion":"SOLAPAMIENTO DE INTERNACIONES"}
,{"c_proceso":4821,"c_file_upload":3398291,"n_prestacion":770,"c_validacion":19,"c_grupo":"4 ","c_id_practica":2860679694,"d_validacion":"SOLAPAMIENTO DE INTERNACIONES"}
,{"c_proceso":4821,"c_file_upload":3398291,"n_prestacion":770,"c_validacion":19,"c_grupo":"4 ","c_id_practica":2860684851,"d_validacion":"SOLAPAMIENTO DE INTERNACIONES"}
,{"c_proceso":4821,"c_file_upload":3398291,"n_prestacion":770,"c_validacion":19,"c_grupo":"4 ","c_id_practica":2860666938,"d_validacion":"SOLAPAMIENTO DE INTERNACIONES"}
,{"c_proceso":4821,"c_file_upload":3398291,"n_prestacion":769,"c_validacion":19,"c_grupo":"4 ","c_id_practica":2860679659,"d_validacion":"SOLAPAMIENTO DE INTERNACIONES"}
,{"c_proceso":4821,"c_file_upload":3398291,"n_prestacion":769,"c_validacion":19,"c_grupo":"4 ","c_id_practica":2860667043,"d_validacion":"SOLAPAMIENTO DE INTERNACIONES"}
,{"c_proceso":4821,"c_file_upload":3398291,"n_prestacion":770,"c_validacion":19,"c_grupo":"4 ","c_id_practica":2860679691,"d_validacion":"SOLAPAMIENTO DE INTERNACIONES"}
,{"c_proceso":4821,"c_file_upload":3398291,"n_prestacion":770,"c_validacion":19,"c_grupo":"4 ","c_id_practica":2860666843,"d_validacion":"SOLAPAMIENTO DE INTERNACIONES"}
,{"c_proceso":4821,"c_file_upload":3398291,"n_prestacion":770,"c_validacion":19,"c_grupo":"4 ","c_id_practica":2860666935,"d_validacion":"SOLAPAMIENTO DE INTERNACIONES"}
,{"c_proceso":4821,"c_file_upload":3398291,"n_prestacion":769,"c_validacion":19,"c_grupo":"4 ","c_id_practica":2860671953,"d_validacion":"SOLAPAMIENTO DE INTERNACIONES"}
,{"c_proceso":4821,"c_file_upload":3398291,"n_prestacion":769,"c_validacion":19,"c_grupo":"4 ","c_id_practica":2860677403,"d_validacion":"SOLAPAMIENTO DE INTERNACIONES"}
,{"c_proceso":4821,"c_file_upload":3398291,"n_prestacion":770,"c_validacion":19,"c_grupo":"4 ","c_id_practica":2860677118,"d_validacion":"SOLAPAMIENTO DE INTERNACIONES"}
,{"c_proceso":4821,"c_file_upload":3398291,"n_prestacion":770,"c_validacion":19,"c_grupo":"4 ","c_id_practica":2860669663,"d_validacion":"SOLAPAMIENTO DE INTERNACIONES"}
,{"c_proceso":4821,"c_file_upload":3398291,"n_prestacion":770,"c_validacion":19,"c_grupo":"4 ","c_id_practica":2860674679,"d_validacion":"SOLAPAMIENTO DE INTERNACIONES"}
,{"c_proceso":4821,"c_file_upload":3398291,"n_prestacion":769,"c_validacion":19,"c_grupo":"4 ","c_id_practica":2860666693,"d_validacion":"SOLAPAMIENTO DE INTERNACIONES"}
,{"c_proceso":4821,"c_file_upload":3398291,"n_prestacion":769,"c_validacion":19,"c_grupo":"4 ","c_id_practica":2860682481,"d_validacion":"SOLAPAMIENTO DE INTERNACIONES"}
,{"c_proceso":4821,"c_file_upload":3398291,"n_prestacion":770,"c_validacion":19,"c_grupo":"4 ","c_id_practica":2860678608,"d_validacion":"SOLAPAMIENTO DE INTERNACIONES"}
,{"c_proceso":4821,"c_file_upload":3398291,"n_prestacion":770,"c_validacion":19,"c_grupo":"4 ","c_id_practica":2860673456,"d_validacion":"SOLAPAMIENTO DE INTERNACIONES"}
,{"c_proceso":4821,"c_file_upload":3398291,"n_prestacion":770,"c_validacion":19,"c_grupo":"4 ","c_id_practica":2860681144,"d_validacion":"SOLAPAMIENTO DE INTERNACIONES"}
,{"c_proceso":4821,"c_file_upload":3398291,"n_prestacion":770,"c_validacion":19,"c_grupo":"4 ","c_id_practica":2860682193,"d_validacion":"SOLAPAMIENTO DE INTERNACIONES"}
,{"c_proceso":4821,"c_file_upload":3398291,"n_prestacion":770,"c_validacion":19,"c_grupo":"4 ","c_id_practica":2860672213,"d_validacion":"SOLAPAMIENTO DE INTERNACIONES"}
,{"c_proceso":4821,"c_file_upload":3398291,"n_prestacion":770,"c_validacion":19,"c_grupo":"4 ","c_id_practica":2860668335,"d_validacion":"SOLAPAMIENTO DE INTERNACIONES"}
,{"c_proceso":4821,"c_file_upload":3398291,"n_prestacion":770,"c_validacion":19,"c_grupo":"4 ","c_id_practica":2860666932,"d_validacion":"SOLAPAMIENTO DE INTERNACIONES"}
,{"c_proceso":4821,"c_file_upload":3398291,"n_prestacion":769,"c_validacion":19,"c_grupo":"4 ","c_id_practica":2860666689,"d_validacion":"SOLAPAMIENTO DE INTERNACIONES"}
,{"c_proceso":4821,"c_file_upload":3398291,"n_prestacion":769,"c_validacion":19,"c_grupo":"4 ","c_id_practica":2860679903,"d_validacion":"SOLAPAMIENTO DE INTERNACIONES"}
,{"c_proceso":4821,"c_file_upload":3398291,"n_prestacion":770,"c_validacion":19,"c_grupo":"4 ","c_id_practica":2860684758,"d_validacion":"SOLAPAMIENTO DE INTERNACIONES"}
,{"c_proceso":4821,"c_file_upload":3398291,"n_prestacion":770,"c_validacion":19,"c_grupo":"4 ","c_id_practica":2860682511,"d_validacion":"SOLAPAMIENTO DE INTERNACIONES"}
,{"c_proceso":4821,"c_file_upload":3398291,"n_prestacion":769,"c_validacion":19,"c_grupo":"4 ","c_id_practica":2860682157,"d_validacion":"SOLAPAMIENTO DE INTERNACIONES"}
,{"c_proceso":4821,"c_file_upload":3398291,"n_prestacion":769,"c_validacion":19,"c_grupo":"4 ","c_id_practica":2860677400,"d_validacion":"SOLAPAMIENTO DE INTERNACIONES"}
,{"c_proceso":4821,"c_file_upload":3398291,"n_prestacion":770,"c_validacion":19,"c_grupo":"4 ","c_id_practica":2860683637,"d_validacion":"SOLAPAMIENTO DE INTERNACIONES"}
,{"c_proceso":4821,"c_file_upload":3398291,"n_prestacion":770,"c_validacion":19,"c_grupo":"4 ","c_id_practica":2860665526,"d_validacion":"SOLAPAMIENTO DE INTERNACIONES"}
,{"c_proceso":4821,"c_file_upload":3398291,"n_prestacion":770,"c_validacion":19,"c_grupo":"4 ","c_id_practica":2860673435,"d_validacion":"SOLAPAMIENTO DE INTERNACIONES"}
,{"c_proceso":4821,"c_file_upload":3398291,"n_prestacion":770,"c_validacion":19,"c_grupo":"4 ","c_id_practica":2860671971,"d_validacion":"SOLAPAMIENTO DE INTERNACIONES"}
,{"c_proceso":4821,"c_file_upload":3398291,"n_prestacion":770,"c_validacion":19,"c_grupo":"4 ","c_id_practica":2860677437,"d_validacion":"SOLAPAMIENTO DE INTERNACIONES"}
,{"c_proceso":4821,"c_file_upload":3398291,"n_prestacion":769,"c_validacion":19,"c_grupo":"4 ","c_id_practica":2860677071,"d_validacion":"SOLAPAMIENTO DE INTERNACIONES"}
,{"c_proceso":4821,"c_file_upload":3398291,"n_prestacion":769,"c_validacion":19,"c_grupo":"4 ","c_id_practica":2860674731,"d_validacion":"SOLAPAMIENTO DE INTERNACIONES"}
,{"c_proceso":4821,"c_file_upload":3398291,"n_prestacion":770,"c_validacion":19,"c_grupo":"4 ","c_id_practica":2860673452,"d_validacion":"SOLAPAMIENTO DE INTERNACIONES"}
,{"c_proceso":4821,"c_file_upload":3398291,"n_prestacion":770,"c_validacion":19,"c_grupo":"4 ","c_id_practica":2860673432,"d_validacion":"SOLAPAMIENTO DE INTERNACIONES"}
,{"c_proceso":4821,"c_file_upload":3398291,"n_prestacion":770,"c_validacion":19,"c_grupo":"4 ","c_id_practica":2860673331,"d_validacion":"SOLAPAMIENTO DE INTERNACIONES"}
,{"c_proceso":4821,"c_file_upload":3398291,"n_prestacion":770,"c_validacion":19,"c_grupo":"4 ","c_id_practica":2860677115,"d_validacion":"SOLAPAMIENTO DE INTERNACIONES"}
,{"c_proceso":4821,"c_file_upload":3398291,"n_prestacion":770,"c_validacion":19,"c_grupo":"4 ","c_id_practica":2860669660,"d_validacion":"SOLAPAMIENTO DE INTERNACIONES"}
,{"c_proceso":4821,"c_file_upload":3398291,"n_prestacion":769,"c_validacion":19,"c_grupo":"4 ","c_id_practica":2860682154,"d_validacion":"SOLAPAMIENTO DE INTERNACIONES"}
,{"c_proceso":4821,"c_file_upload":3398291,"n_prestacion":769,"c_validacion":19,"c_grupo":"4 ","c_id_practica":2860679900,"d_validacion":"SOLAPAMIENTO DE INTERNACIONES"}
,{"c_proceso":4821,"c_file_upload":3398291,"n_prestacion":770,"c_validacion":19,"c_grupo":"4 ","c_id_practica":2860679689,"d_validacion":"SOLAPAMIENTO DE INTERNACIONES"}
,{"c_proceso":4821,"c_file_upload":3398291,"n_prestacion":770,"c_validacion":19,"c_grupo":"4 ","c_id_practica":2860682508,"d_validacion":"SOLAPAMIENTO DE INTERNACIONES"}
,{"c_proceso":4821,"c_file_upload":3398291,"n_prestacion":769,"c_validacion":19,"c_grupo":"4 ","c_id_practica":2860679656,"d_validacion":"SOLAPAMIENTO DE INTERNACIONES"}
,{"c_proceso":4821,"c_file_upload":3398291,"n_prestacion":769,"c_validacion":19,"c_grupo":"4 ","c_id_practica":2860679897,"d_validacion":"SOLAPAMIENTO DE INTERNACIONES"}
,{"c_proceso":4821,"c_file_upload":3398291,"n_prestacion":769,"c_validacion":19,"c_grupo":"4 ","c_id_practica":2860682152,"d_validacion":"SOLAPAMIENTO DE INTERNACIONES"}
,{"c_proceso":4821,"c_file_upload":3398291,"n_prestacion":769,"c_validacion":19,"c_grupo":"4 ","c_id_practica":2860677397,"d_validacion":"SOLAPAMIENTO DE INTERNACIONES"}
,{"c_proceso":4821,"c_file_upload":3398291,"n_prestacion":769,"c_validacion":19,"c_grupo":"4 ","c_id_practica":2860677068,"d_validacion":"SOLAPAMIENTO DE INTERNACIONES"}
,{"c_proceso":4821,"c_file_upload":3398291,"n_prestacion":769,"c_validacion":19,"c_grupo":"4 ","c_id_practica":2860674729,"d_validacion":"SOLAPAMIENTO DE INTERNACIONES"}
,{"c_proceso":4821,"c_file_upload":3398291,"n_prestacion":769,"c_validacion":19,"c_grupo":"4 ","c_id_practica":2860679654,"d_validacion":"SOLAPAMIENTO DE INTERNACIONES"}
,{"c_proceso":4821,"c_file_upload":3398291,"n_prestacion":769,"c_validacion":19,"c_grupo":"4 ","c_id_practica":2860667039,"d_validacion":"SOLAPAMIENTO DE INTERNACIONES"}
,{"c_proceso":4821,"c_file_upload":3398291,"n_prestacion":769,"c_validacion":19,"c_grupo":"4 ","c_id_practica":2860677065,"d_validacion":"SOLAPAMIENTO DE INTERNACIONES"}
,{"c_proceso":4821,"c_file_upload":3398291,"n_prestacion":769,"c_validacion":19,"c_grupo":"4 ","c_id_practica":2860672195,"d_validacion":"SOLAPAMIENTO DE INTERNACIONES"}
,{"c_proceso":4821,"c_file_upload":3398291,"n_prestacion":769,"c_validacion":19,"c_grupo":"4 ","c_id_practica":2860671950,"d_validacion":"SOLAPAMIENTO DE INTERNACIONES"}
,{"c_proceso":4821,"c_file_upload":3398291,"n_prestacion":769,"c_validacion":19,"c_grupo":"4 ","c_id_practica":2860682478,"d_validacion":"SOLAPAMIENTO DE INTERNACIONES"}
,{"c_proceso":4821,"c_file_upload":3398291,"n_prestacion":769,"c_validacion":19,"c_grupo":"4 ","c_id_practica":2860677062,"d_validacion":"SOLAPAMIENTO DE INTERNACIONES"}
,{"c_proceso":4821,"c_file_upload":3398291,"n_prestacion":769,"c_validacion":19,"c_grupo":"4 ","c_id_practica":2860669626,"d_validacion":"SOLAPAMIENTO DE INTERNACIONES"}
,{"c_proceso":4821,"c_file_upload":3398291,"n_prestacion":769,"c_validacion":19,"c_grupo":"4 ","c_id_practica":2860684727,"d_validacion":"SOLAPAMIENTO DE INTERNACIONES"}
,{"c_proceso":4821,"c_file_upload":3398291,"n_prestacion":769,"c_validacion":19,"c_grupo":"4 ","c_id_practica":2860669623,"d_validacion":"SOLAPAMIENTO DE INTERNACIONES"}
,{"c_proceso":4821,"c_file_upload":3398291,"n_prestacion":769,"c_validacion":19,"c_grupo":"4 ","c_id_practica":2860666686,"d_validacion":"SOLAPAMIENTO DE INTERNACIONES"}
,{"c_proceso":4821,"c_file_upload":3398291,"n_prestacion":769,"c_validacion":19,"c_grupo":"4 ","c_id_practica":2860685065,"d_validacion":"SOLAPAMIENTO DE INTERNACIONES"}
,{"c_proceso":4821,"c_file_upload":3398291,"n_prestacion":769,"c_validacion":19,"c_grupo":"4 ","c_id_practica":2860679652,"d_validacion":"SOLAPAMIENTO DE INTERNACIONES"}
,{"c_proceso":4821,"c_file_upload":3398291,"n_prestacion":769,"c_validacion":19,"c_grupo":"4 ","c_id_practica":2860672192,"d_validacion":"SOLAPAMIENTO DE INTERNACIONES"}
,{"c_proceso":4821,"c_file_upload":3398291,"n_prestacion":769,"c_validacion":19,"c_grupo":"4 ","c_id_practica":2860677060,"d_validacion":"SOLAPAMIENTO DE INTERNACIONES"}
,{"c_proceso":4821,"c_file_upload":3398291,"n_prestacion":769,"c_validacion":19,"c_grupo":"4 ","c_id_practica":2860682475,"d_validacion":"SOLAPAMIENTO DE INTERNACIONES"}
,{"c_proceso":4821,"c_file_upload":3398291,"n_prestacion":769,"c_validacion":19,"c_grupo":"4 ","c_id_practica":2860679648,"d_validacion":"SOLAPAMIENTO DE INTERNACIONES"}
,{"c_proceso":4821,"c_file_upload":3398291,"n_prestacion":769,"c_validacion":19,"c_grupo":"4 ","c_id_practica":2860685063,"d_validacion":"SOLAPAMIENTO DE INTERNACIONES"}
,{"c_proceso":4821,"c_file_upload":3398291,"n_prestacion":769,"c_validacion":19,"c_grupo":"4 ","c_id_practica":2860674420,"d_validacion":"SOLAPAMIENTO DE INTERNACIONES"}
,{"c_proceso":4821,"c_file_upload":3398291,"n_prestacion":769,"c_validacion":19,"c_grupo":"4 ","c_id_practica":2860682472,"d_validacion":"SOLAPAMIENTO DE INTERNACIONES"}
,{"c_proceso":4821,"c_file_upload":3398291,"n_prestacion":769,"c_validacion":19,"c_grupo":"4 ","c_id_practica":2860682149,"d_validacion":"SOLAPAMIENTO DE INTERNACIONES"}
,{"c_proceso":4821,"c_file_upload":3398291,"n_prestacion":769,"c_validacion":19,"c_grupo":"4 ","c_id_practica":2860679894,"d_validacion":"SOLAPAMIENTO DE INTERNACIONES"}
,{"c_proceso":4821,"c_file_upload":3398291,"n_prestacion":769,"c_validacion":19,"c_grupo":"4 ","c_id_practica":2860671946,"d_validacion":"SOLAPAMIENTO DE INTERNACIONES"}
,{"c_proceso":4821,"c_file_upload":3398291,"n_prestacion":769,"c_validacion":19,"c_grupo":"4 ","c_id_practica":2860669620,"d_validacion":"SOLAPAMIENTO DE INTERNACIONES"}
,{"c_proceso":4821,"c_file_upload":3398291,"n_prestacion":769,"c_validacion":19,"c_grupo":"4 ","c_id_practica":2860674417,"d_validacion":"SOLAPAMIENTO DE INTERNACIONES"}
,{"c_proceso":4821,"c_file_upload":3398291,"n_prestacion":769,"c_validacion":19,"c_grupo":"4 ","c_id_practica":2860685059,"d_validacion":"SOLAPAMIENTO DE INTERNACIONES"}
,{"c_proceso":4821,"c_file_upload":3398291,"n_prestacion":680,"c_validacion":19,"c_grupo":"4 ","c_id_practica":2860669020,"d_validacion":"SOLAPAMIENTO DE INTERNACIONES"}
,{"c_proceso":4821,"c_file_upload":3398291,"n_prestacion":680,"c_validacion":19,"c_grupo":"4 ","c_id_practica":2860674704,"d_validacion":"SOLAPAMIENTO DE INTERNACIONES"}
,{"c_proceso":4821,"c_file_upload":3398291,"n_prestacion":680,"c_validacion":19,"c_grupo":"4 ","c_id_practica":2860680651,"d_validacion":"SOLAPAMIENTO DE INTERNACIONES"}
,{"c_proceso":4821,"c_file_upload":3398291,"n_prestacion":680,"c_validacion":19,"c_grupo":"4 ","c_id_practica":2860673418,"d_validacion":"SOLAPAMIENTO DE INTERNACIONES"}
,{"c_proceso":4821,"c_file_upload":3398291,"n_prestacion":680,"c_validacion":19,"c_grupo":"4 ","c_id_practica":2860668326,"d_validacion":"SOLAPAMIENTO DE INTERNACIONES"}
,{"c_proceso":4821,"c_file_upload":3398291,"n_prestacion":680,"c_validacion":19,"c_grupo":"4 ","c_id_practica":2860669195,"d_validacion":"SOLAPAMIENTO DE INTERNACIONES"}
,{"c_proceso":4821,"c_file_upload":3398291,"n_prestacion":769,"c_validacion":19,"c_grupo":"4 ","c_id_practica":2860679646,"d_validacion":"SOLAPAMIENTO DE INTERNACIONES"}
,{"c_proceso":4821,"c_file_upload":3398291,"n_prestacion":769,"c_validacion":19,"c_grupo":"4 ","c_id_practica":2860685053,"d_validacion":"SOLAPAMIENTO DE INTERNACIONES"}
,{"c_proceso":4821,"c_file_upload":3398291,"n_prestacion":769,"c_validacion":19,"c_grupo":"4 ","c_id_practica":2860674426,"d_validacion":"SOLAPAMIENTO DE INTERNACIONES"}
,{"c_proceso":4821,"c_file_upload":3398291,"n_prestacion":769,"c_validacion":19,"c_grupo":"4 ","c_id_practica":2860685056,"d_validacion":"SOLAPAMIENTO DE INTERNACIONES"}
,{"c_proceso":4821,"c_file_upload":3398291,"n_prestacion":680,"c_validacion":46,"c_grupo":"11","c_id_practica":2860670926,"d_validacion":"FUERA DE RANGO - MENSUAL"}
,{"c_proceso":4821,"c_file_upload":3398291,"n_prestacion":769,"c_validacion":42,"c_grupo":"9 ","c_id_practica":2860667265,"d_validacion":"PRACTICA NO AUTORIZADA EN LA ORDEN DE PRESTACION"}
,{"c_proceso":4821,"c_file_upload":3398291,"n_prestacion":769,"c_validacion":42,"c_grupo":"9 ","c_id_practica":2860685485,"d_validacion":"PRACTICA NO AUTORIZADA EN LA ORDEN DE PRESTACION"}
,{"c_proceso":4821,"c_file_upload":3398291,"n_prestacion":680,"c_validacion":19,"c_grupo":"4 ","c_id_practica":2860685300,"d_validacion":"SOLAPAMIENTO DE INTERNACIONES"}
,{"c_proceso":4821,"c_file_upload":3398291,"n_prestacion":680,"c_validacion":42,"c_grupo":"9 ","c_id_practica":2860685300,"d_validacion":"PRACTICA NO AUTORIZADA EN LA ORDEN DE PRESTACION"}
,{"c_proceso":4821,"c_file_upload":3398291,"n_prestacion":680,"c_validacion":19,"c_grupo":"4 ","c_id_practica":2860677816,"d_validacion":"SOLAPAMIENTO DE INTERNACIONES"}
,{"c_proceso":4821,"c_file_upload":3398291,"n_prestacion":680,"c_validacion":42,"c_grupo":"9 ","c_id_practica":2860677816,"d_validacion":"PRACTICA NO AUTORIZADA EN LA ORDEN DE PRESTACION"}
,{"c_proceso":4821,"c_file_upload":3398291,"n_prestacion":769,"c_validacion":42,"c_grupo":"9 ","c_id_practica":2860670323,"d_validacion":"PRACTICA NO AUTORIZADA EN LA ORDEN DE PRESTACION"}
,{"c_proceso":4821,"c_file_upload":3398291,"n_prestacion":769,"c_validacion":42,"c_grupo":"9 ","c_id_practica":2860678087,"d_validacion":"PRACTICA NO AUTORIZADA EN LA ORDEN DE PRESTACION"}
,{"c_proceso":4821,"c_file_upload":3398291,"n_prestacion":769,"c_validacion":42,"c_grupo":"9 ","c_id_practica":2860675256,"d_validacion":"PRACTICA NO AUTORIZADA EN LA ORDEN DE PRESTACION"}
,{"c_proceso":4821,"c_file_upload":3398291,"n_prestacion":770,"c_validacion":19,"c_grupo":"4 ","c_id_practica":2860683168,"d_validacion":"SOLAPAMIENTO DE INTERNACIONES"}
,{"c_proceso":4821,"c_file_upload":3398291,"n_prestacion":770,"c_validacion":42,"c_grupo":"9 ","c_id_practica":2860683168,"d_validacion":"PRACTICA NO AUTORIZADA EN LA ORDEN DE PRESTACION"}
,{"c_proceso":4821,"c_file_upload":3398291,"n_prestacion":770,"c_validacion":19,"c_grupo":"4 ","c_id_practica":2860673028,"d_validacion":"SOLAPAMIENTO DE INTERNACIONES"}
,{"c_proceso":4821,"c_file_upload":3398291,"n_prestacion":770,"c_validacion":42,"c_grupo":"9 ","c_id_practica":2860673028,"d_validacion":"PRACTICA NO AUTORIZADA EN LA ORDEN DE PRESTACION"}
,{"c_proceso":4821,"c_file_upload":3398291,"n_prestacion":680,"c_validacion":42,"c_grupo":"9 ","c_id_practica":2860672713,"d_validacion":"PRACTICA NO AUTORIZADA EN LA ORDEN DE PRESTACION"}
,{"c_proceso":4821,"c_file_upload":3398291,"n_prestacion":680,"c_validacion":42,"c_grupo":"9 ","c_id_practica":2860675623,"d_validacion":"PRACTICA NO AUTORIZADA EN LA ORDEN DE PRESTACION"}
,{"c_proceso":4821,"c_file_upload":3398291,"n_prestacion":680,"c_validacion":42,"c_grupo":"9 ","c_id_practica":2860667980,"d_validacion":"PRACTICA NO AUTORIZADA EN LA ORDEN DE PRESTACION"}
,{"c_proceso":4821,"c_file_upload":3398291,"n_prestacion":680,"c_validacion":42,"c_grupo":"9 ","c_id_practica":2860675637,"d_validacion":"PRACTICA NO AUTORIZADA EN LA ORDEN DE PRESTACION"}
]}]}